{
  "name": "Top 100 Power Ballads",
  "version": "1.0",
  "tags": [
    "1980s",
    "1990s",
    "rock",
    "ballads",
    "international"
  ],
  "songs": [
    {
      "year": 1998,
      "uri": "spotify:track:021vWlv02jZVfMYYVPsjDT",
      "artist": "Aerosmith",
      "alt_artists": [
        "Bon Jovi",
        "Def Leppard"
      ],
      "title": "I Don't Want to Miss a Thing - From \"Armageddon\" Soundtrack",
      "chart_info": {
        "billboard_peak": 1,
        "uk_peak": 4,
        "weeks_on_chart": 21
      },
      "certifications": [
        "4x Platinum (US)",
        "Platinum (UK)"
      ],
      "awards": [],
      "fun_fact": "Written by Diane Warren in just 4 hours. Steven Tyler initially didn't want to record it, but it became Aerosmith's only #1 hit. The song was inspired by Warren watching someone sleep and not wanting to close her eyes.",
      "fun_fact_de": "[DE] Written by Diane Warren in just 4 hours. Steven Tyler initially didn't want to r...",
      "fun_fact_es": "[ES] Written by Diane Warren in just 4 hours. Steven Tyler initially didn't want to r...",
      "uri_apple_music": "applemusic://track/1660108804",
      "uri_youtube_music": "https://music.youtube.com/watch?v=JkK8g6FMEXE",
      "uri_tidal": "tidal://track/61126692"
    },
    {
      "year": 1992,
      "uri": "spotify:track:02pW89yEg8BHmkQWf1RTMF",
      "artist": "Guns N' Roses",
      "alt_artists": [
        "Skid Row",
        "Mötley Crüe"
      ],
      "title": "November Rain",
      "chart_info": {
        "billboard_peak": 3,
        "uk_peak": 4,
        "weeks_on_chart": 20
      },
      "certifications": [
        "2x Platinum (US)",
        "Platinum (UK)"
      ],
      "awards": [],
      "fun_fact": "At 8:57, it was the longest song to crack the top 10 since 'American Pie'. The lavish music video cost $1.5 million and was filmed at a real wedding chapel in Las Vegas.",
      "fun_fact_de": "[DE] At 8:57, it was the longest song to crack the top 10 since 'American Pie'. The l...",
      "fun_fact_es": "[ES] At 8:57, it was the longest song to crack the top 10 since 'American Pie'. The l...",
      "uri_apple_music": "applemusic://track/1440896193",
      "uri_youtube_music": "https://music.youtube.com/watch?v=8SbUC-UaAxE",
      "uri_tidal": "tidal://track/10902755"
    },
    {
      "year": 1984,
      "uri": "spotify:track:0A8HK5hV5SgywiKKrBPKDU",
      "artist": "Foreigner",
      "alt_artists": [
        "Journey",
        "REO Speedwagon"
      ],
      "title": "I Want to Know What Love Is - 1999 Remaster",
      "chart_info": {
        "billboard_peak": 0,
        "uk_peak": 0,
        "weeks_on_chart": 0
      },
      "certifications": [],
      "awards": [],
      "fun_fact": "A classic power ballad by Foreigner.",
      "fun_fact_de": "",
      "fun_fact_es": "",
      "uri_apple_music": "applemusic://track/216663961",
      "uri_youtube_music": "https://music.youtube.com/watch?v=r3Pr1_v7hsw",
      "uri_tidal": "tidal://track/637081"
    },
    {
      "year": 1993,
      "uri": "spotify:track:0AfIsqZ4gTUg9CwwW2jLeK",
      "artist": "Meat Loaf",
      "alt_artists": [
        "Bonnie Tyler",
        "Jim Steinman"
      ],
      "title": "I'd Do Anything For Love (But I Won't Do That)",
      "chart_info": {
        "billboard_peak": 1,
        "uk_peak": 1,
        "weeks_on_chart": 22
      },
      "certifications": [
        "2x Platinum (US)",
        "Platinum (UK)"
      ],
      "awards": [],
      "fun_fact": "The 'that' refers to various things mentioned throughout the song - not one specific act. Jim Steinman's epic production took over 3 months to complete.",
      "fun_fact_de": "[DE] The 'that' refers to various things mentioned throughout the song - not one spec...",
      "fun_fact_es": "[ES] The 'that' refers to various things mentioned throughout the song - not one spec...",
      "uri_apple_music": "applemusic://track/1452850583",
      "uri_youtube_music": "https://music.youtube.com/watch?v=9X_ViIPA-Gc",
      "uri_tidal": "tidal://track/703088"
    },
    {
      "year": 1987,
      "uri": "spotify:track:0KMGxYKeUzK9wc5DZCt3HT",
      "artist": "U2",
      "alt_artists": [
        "Simple Minds",
        "INXS"
      ],
      "title": "With Or Without You",
      "chart_info": {
        "billboard_peak": 1,
        "uk_peak": 4,
        "weeks_on_chart": 18
      },
      "certifications": [
        "Platinum (US)",
        "Gold (UK)"
      ],
      "awards": [],
      "fun_fact": "U2's first US #1. The Edge used an Infinite Guitar prototype that created the song's distinctive sustained notes. Bono wrote the lyrics in 10 minutes.",
      "fun_fact_de": "[DE] U2's first US #1. The Edge used an Infinite Guitar prototype that created the so...",
      "fun_fact_es": "[ES] U2's first US #1. The Edge used an Infinite Guitar prototype that created the so...",
      "uri_apple_music": "applemusic://track/1440729860",
      "uri_youtube_music": "https://music.youtube.com/watch?v=ujNeHIo7oTE",
      "uri_tidal": "tidal://track/207292"
    },
    {
      "year": 1991,
      "uri": "spotify:track:0YPXkQthLWrhNGoKTbwCJ8",
      "artist": "Bryan Adams",
      "alt_artists": [
        "Richard Marx",
        "Michael Bolton"
      ],
      "title": "(Everything I Do) I Do It For You",
      "chart_info": {
        "billboard_peak": 1,
        "uk_peak": 1,
        "weeks_on_chart": 24
      },
      "certifications": [
        "4x Platinum (US)",
        "2x Platinum (UK)"
      ],
      "awards": [],
      "fun_fact": "Spent 16 consecutive weeks at #1 in the UK - still a record. Written for Robin Hood: Prince of Thieves, it was composed in 45 minutes.",
      "fun_fact_de": "[DE] Spent 16 consecutive weeks at #1 in the UK - still a record. Written for Robin H...",
      "fun_fact_es": "[ES] Spent 16 consecutive weeks at #1 in the UK - still a record. Written for Robin H...",
      "uri_apple_music": "applemusic://track/1870995778",
      "uri_youtube_music": "https://music.youtube.com/watch?v=Y0pdQU87dc8",
      "uri_tidal": "tidal://track/1330631"
    },
    {
      "year": 1980,
      "uri": "spotify:track:0Yi128S6QgQDnAKg5A0OZw",
      "artist": "REO Speedwagon",
      "alt_artists": [
        "Styx",
        "Journey"
      ],
      "title": "Keep on Loving You",
      "chart_info": {
        "billboard_peak": 1,
        "uk_peak": 7,
        "weeks_on_chart": 21
      },
      "certifications": [
        "Platinum (US)"
      ],
      "awards": [],
      "fun_fact": "Kevin Cronin wrote this after a real argument with his girlfriend where she caught him lying. The song's success transformed REO from an arena rock band to pop superstars.",
      "fun_fact_de": "[DE] Kevin Cronin wrote this after a real argument with his girlfriend where she caug...",
      "fun_fact_es": "[ES] Kevin Cronin wrote this after a real argument with his girlfriend where she caug...",
      "uri_apple_music": "applemusic://track/447759252",
      "uri_youtube_music": "https://music.youtube.com/watch?v=wJzNZ1c5C9c",
      "uri_tidal": "tidal://track/77447199"
    },
    {
      "year": 1992,
      "uri": "spotify:track:0ZEhlT9v8CdOKu55zhYGv9",
      "artist": "Metallica",
      "alt_artists": [
        "Scorpions",
        "Iron Maiden"
      ],
      "title": "Nothing Else Matters",
      "chart_info": {
        "billboard_peak": 34,
        "uk_peak": 6,
        "weeks_on_chart": 15
      },
      "certifications": [
        "Platinum (US)",
        "Gold (UK)"
      ],
      "awards": [],
      "fun_fact": "James Hetfield wrote this while on the phone with his girlfriend, playing one-handed. He never intended for the band to hear it, considering it too personal.",
      "fun_fact_de": "[DE] James Hetfield wrote this while on the phone with his girlfriend, playing one-ha...",
      "fun_fact_es": "[ES] James Hetfield wrote this while on the phone with his girlfriend, playing one-ha...",
      "uri_apple_music": "applemusic://track/1572046444",
      "uri_youtube_music": "https://music.youtube.com/watch?v=tAGnKpE4NCI",
      "uri_tidal": "tidal://track/629055"
    },
    {
      "year": 1996,
      "uri": "spotify:track:0gmbgwZ8iqyMPmXefof8Yf",
      "artist": "Céline Dion",
      "alt_artists": [
        "Whitney Houston",
        "Mariah Carey"
      ],
      "title": "All By Myself",
      "chart_info": {
        "billboard_peak": 4,
        "uk_peak": 6,
        "weeks_on_chart": 16
      },
      "certifications": [
        "Gold (US)",
        "Silver (UK)"
      ],
      "awards": [],
      "fun_fact": "Originally a 1975 hit by Eric Carmen, who based the melody on Rachmaninoff. Céline's powerful version showcased her incredible vocal range and became a karaoke staple.",
      "fun_fact_de": "[DE] Originally a 1975 hit by Eric Carmen, who based the melody on Rachmaninoff. Céli...",
      "fun_fact_es": "[ES] Originally a 1975 hit by Eric Carmen, who based the melody on Rachmaninoff. Céli...",
      "uri_apple_music": "applemusic://track/1473319811",
      "uri_youtube_music": "https://music.youtube.com/watch?v=NGrLb6W5YOM",
      "uri_tidal": "tidal://track/23267439"
    },
    {
      "year": 1985,
      "uri": "spotify:track:0mYPfHvPzoUZJ2puHRyzyf",
      "artist": "Mr. Mister",
      "alt_artists": [
        "Toto",
        "Chicago"
      ],
      "title": "Broken Wings",
      "chart_info": {
        "billboard_peak": 1,
        "uk_peak": 4,
        "weeks_on_chart": 19
      },
      "certifications": [
        "Gold (US)"
      ],
      "awards": [],
      "fun_fact": "The title comes from the Kahlil Gibran book 'Broken Wings'. Richard Page wrote the song about helping a friend through difficult times.",
      "fun_fact_de": "[DE] The title comes from the Kahlil Gibran book 'Broken Wings'. Richard Page wrote t...",
      "fun_fact_es": "[ES] The title comes from the Kahlil Gibran book 'Broken Wings'. Richard Page wrote t...",
      "uri_apple_music": "applemusic://track/303089712",
      "uri_youtube_music": "https://music.youtube.com/watch?v=nKhN1t_7PEY",
      "uri_tidal": "tidal://track/572144"
    },
    {
      "year": 1988,
      "uri": "spotify:track:0tP5ogrxKrIPKHHc0seuOr",
      "artist": "Van Halen",
      "alt_artists": [
        "Bon Jovi",
        "Def Leppard"
      ],
      "title": "When It's Love - 2004 Remaster",
      "chart_info": {
        "billboard_peak": 5,
        "uk_peak": 28,
        "weeks_on_chart": 16
      },
      "certifications": [
        "Gold (US)"
      ],
      "awards": [],
      "fun_fact": "One of Van Halen's most successful ballads with Sammy Hagar. Eddie Van Halen's keyboard work showcased the band's evolved sound from their early hard rock days.",
      "fun_fact_de": "[DE] One of Van Halen's most successful ballads with Sammy Hagar. Eddie Van Halen's k...",
      "fun_fact_es": "[ES] One of Van Halen's most successful ballads with Sammy Hagar. Eddie Van Halen's k...",
      "uri_apple_music": "applemusic://track/319580987",
      "uri_youtube_music": "https://music.youtube.com/watch?v=OZGXRCI-JzQ",
      "uri_tidal": "tidal://track/1218919"
    },
    {
      "year": 1986,
      "uri": "spotify:track:0usJ6ywAqqeJx1nQl5SWlP",
      "artist": "Heart",
      "alt_artists": [
        "Pat Benatar",
        "Joan Jett"
      ],
      "title": "These Dreams",
      "chart_info": {
        "billboard_peak": 1,
        "uk_peak": 62,
        "weeks_on_chart": 17
      },
      "certifications": [
        "Gold (US)"
      ],
      "awards": [],
      "fun_fact": "Written by Bernie Taupin and Martin Page, this became Heart's first #1 hit. Nancy Wilson sang lead instead of Ann because her softer voice better suited the dreamy lyrics.",
      "fun_fact_de": "[DE] Written by Bernie Taupin and Martin Page, this became Heart's first #1 hit. Nanc...",
      "fun_fact_es": "[ES] Written by Bernie Taupin and Martin Page, this became Heart's first #1 hit. Nanc...",
      "uri_apple_music": "applemusic://track/1441162329",
      "uri_youtube_music": "https://music.youtube.com/watch?v=41P8UxneDJE",
      "uri_tidal": "tidal://track/35728806"
    },
    {
      "year": 1987,
      "uri": "spotify:track:0z0xo3HAnN8H3FPkNjlEve",
      "artist": "Whitesnake",
      "alt_artists": [
        "Def Leppard",
        "Bon Jovi"
      ],
      "title": "Is This Love",
      "chart_info": {
        "billboard_peak": 2,
        "uk_peak": 9,
        "weeks_on_chart": 18
      },
      "certifications": [
        "Platinum (US)",
        "Gold (UK)"
      ],
      "awards": [],
      "fun_fact": "David Coverdale wrote this for his then-girlfriend Tawny Kitaen, who starred in the iconic video. The song was inspired by his desire to prove he could write tender ballads.",
      "fun_fact_de": "[DE] David Coverdale wrote this for his then-girlfriend Tawny Kitaen, who starred in ...",
      "fun_fact_es": "[ES] David Coverdale wrote this for his then-girlfriend Tawny Kitaen, who starred in ...",
      "uri_apple_music": "applemusic://track/1440611252",
      "uri_youtube_music": "https://music.youtube.com/watch?v=GOJk0HW_hJw",
      "uri_tidal": "tidal://track/314856703"
    },
    {
      "year": 1990,
      "uri": "spotify:track:11R0Wyq7eaxXsWbxfO4Ge7",
      "artist": "Roxette",
      "alt_artists": [
        "ABBA",
        "Ace of Base"
      ],
      "title": "It Must Have Been Love - From the Film \"Pretty Woman\"",
      "chart_info": {
        "billboard_peak": 1,
        "uk_peak": 3,
        "weeks_on_chart": 20
      },
      "certifications": [
        "Platinum (US)",
        "Gold (UK)"
      ],
      "awards": [],
      "fun_fact": "Originally written as a Christmas song in 1987. It was re-recorded for Pretty Woman and became Roxette's biggest international hit.",
      "fun_fact_de": "[DE] Originally written as a Christmas song in 1987. It was re-recorded for Pretty Wo...",
      "fun_fact_es": "[ES] Originally written as a Christmas song in 1987. It was re-recorded for Pretty Wo...",
      "uri_apple_music": "applemusic://track/976541447",
      "uri_youtube_music": "https://music.youtube.com/watch?v=k2C5TjS2sh4",
      "uri_tidal": "tidal://track/277252292"
    },
    {
      "year": 1996,
      "uri": "spotify:track:19itmQVtwhAbICMMDUqDPp",
      "artist": "No Doubt",
      "alt_artists": [
        "The Cranberries",
        "Garbage"
      ],
      "title": "Don't Speak",
      "chart_info": {
        "billboard_peak": 1,
        "uk_peak": 1,
        "weeks_on_chart": 23
      },
      "certifications": [
        "Platinum (US)",
        "Platinum (UK)"
      ],
      "awards": [],
      "fun_fact": "Written by Gwen Stefani about her breakup with bassist Tony Kanal while still in the band. The emotional tension during recording is palpable in the final track.",
      "fun_fact_de": "[DE] Written by Gwen Stefani about her breakup with bassist Tony Kanal while still in...",
      "fun_fact_es": "[ES] Written by Gwen Stefani about her breakup with bassist Tony Kanal while still in...",
      "uri_apple_music": "applemusic://track/1440845557",
      "uri_youtube_music": "https://music.youtube.com/watch?v=TR3Vdo5etCQ",
      "uri_tidal": "tidal://track/268979931"
    },
    {
      "year": 1976,
      "uri": "spotify:track:1EB3Z38oKDKVp4K2yEO2dl",
      "artist": "Chicago",
      "alt_artists": [
        "Toto",
        "Foreigner"
      ],
      "title": "If You Leave Me Now",
      "chart_info": {
        "billboard_peak": 1,
        "uk_peak": 1,
        "weeks_on_chart": 18
      },
      "certifications": [
        "Gold (US)",
        "Silver (UK)"
      ],
      "awards": [],
      "fun_fact": "Peter Cetera wrote this after a breakup. It was Chicago's first #1 hit and won the Grammy for Best Pop Vocal Performance. The band initially didn't want to include it on the album.",
      "fun_fact_de": "[DE] Peter Cetera wrote this after a breakup. It was Chicago's first #1 hit and won t...",
      "fun_fact_es": "[ES] Peter Cetera wrote this after a breakup. It was Chicago's first #1 hit and won t...",
      "uri_apple_music": "applemusic://track/28458011",
      "uri_youtube_music": "https://music.youtube.com/watch?v=-9_d-sFhmRM",
      "uri_tidal": "tidal://track/1331974"
    },
    {
      "year": 2001,
      "uri": "spotify:track:1HlGblweLq0eAwnb0NY1EQ",
      "artist": "Nickelback",
      "alt_artists": [
        "3 Doors Down",
        "Creed"
      ],
      "title": "How You Remind Me",
      "chart_info": {
        "billboard_peak": 1,
        "uk_peak": 4,
        "weeks_on_chart": 24
      },
      "certifications": [
        "4x Platinum (US)",
        "Gold (UK)"
      ],
      "awards": [],
      "fun_fact": "The most-played song on US radio in the 2000s decade. Chad Kroeger wrote it in 10 minutes after a night of drinking, reflecting on a troubled relationship.",
      "fun_fact_de": "[DE] The most-played song on US radio in the 2000s decade. Chad Kroeger wrote it in 1...",
      "fun_fact_es": "[ES] The most-played song on US radio in the 2000s decade. Chad Kroeger wrote it in 1...",
      "uri_apple_music": "applemusic://track/214475478",
      "uri_youtube_music": "https://music.youtube.com/watch?v=Aiay8I5IPB8",
      "uri_tidal": "tidal://track/68665696"
    },
    {
      "year": 1991,
      "uri": "spotify:track:1JLn8RhQzHz3qDqsChcmBl",
      "artist": "Extreme",
      "alt_artists": [
        "Mr. Big",
        "Tesla"
      ],
      "title": "More Than Words",
      "chart_info": {
        "billboard_peak": 1,
        "uk_peak": 2,
        "weeks_on_chart": 19
      },
      "certifications": [
        "Platinum (US)",
        "Gold (UK)"
      ],
      "awards": [],
      "fun_fact": "The band was worried this acoustic ballad would hurt their rock credibility. It became their biggest hit and showcased Nuno Bettencourt's intricate fingerpicking style.",
      "fun_fact_de": "[DE] The band was worried this acoustic ballad would hurt their rock credibility. It ...",
      "fun_fact_es": "[ES] The band was worried this acoustic ballad would hurt their rock credibility. It ...",
      "uri_apple_music": "applemusic://track/1445752097",
      "uri_youtube_music": "https://music.youtube.com/watch?v=UrIiLvg58SY",
      "uri_tidal": "tidal://track/261597"
    },
    {
      "year": 1982,
      "uri": "spotify:track:1JZZkORheU1RpGqJdZ77WL",
      "artist": "Journey",
      "alt_artists": [
        "Foreigner",
        "REO Speedwagon"
      ],
      "title": "Open Arms",
      "chart_info": {
        "billboard_peak": 2,
        "uk_peak": 43,
        "weeks_on_chart": 17
      },
      "certifications": [
        "Gold (US)"
      ],
      "awards": [],
      "fun_fact": "Steve Perry co-wrote this with Jonathan Cain. It was almost left off the Escape album but became one of Journey's most beloved songs, covered by Mariah Carey in 1996.",
      "fun_fact_de": "[DE] Steve Perry co-wrote this with Jonathan Cain. It was almost left off the Escape ...",
      "fun_fact_es": "[ES] Steve Perry co-wrote this with Jonathan Cain. It was almost left off the Escape ...",
      "uri_apple_music": "applemusic://track/159174191",
      "uri_youtube_music": "https://music.youtube.com/watch?v=i5pUOVC50Y8",
      "uri_tidal": "tidal://track/138804"
    },
    {
      "year": 1988,
      "uri": "spotify:track:1KU5EHSz04JhGg3rReGJ0N",
      "artist": "Poison",
      "alt_artists": [
        "Bon Jovi",
        "Warrant"
      ],
      "title": "Every Rose Has Its Thorn - 2003 Remaster",
      "chart_info": {
        "billboard_peak": 1,
        "uk_peak": 13,
        "weeks_on_chart": 20
      },
      "certifications": [
        "2x Platinum (US)"
      ],
      "awards": [],
      "fun_fact": "Bret Michaels wrote this in a laundromat after calling his girlfriend from a payphone and hearing another man answer. It's one of the defining power ballads of the 80s.",
      "fun_fact_de": "[DE] Bret Michaels wrote this in a laundromat after calling his girlfriend from a pay...",
      "fun_fact_es": "[ES] Bret Michaels wrote this in a laundromat after calling his girlfriend from a pay...",
      "uri_apple_music": "applemusic://track/716552556",
      "uri_youtube_music": "https://music.youtube.com/watch?v=j2r2nDhTzO4",
      "uri_tidal": "tidal://track/393496"
    },
    {
      "year": 1991,
      "uri": "spotify:track:1UrZVcINJBqjKw2rF8V0nm",
      "artist": "Scorpions",
      "alt_artists": [
        "Def Leppard",
        "Whitesnake"
      ],
      "title": "Wind Of Change",
      "chart_info": {
        "billboard_peak": 4,
        "uk_peak": 2,
        "weeks_on_chart": 18
      },
      "certifications": [
        "Platinum (US)",
        "Platinum (UK)"
      ],
      "awards": [],
      "fun_fact": "Written after the Scorpions played the Moscow Music Peace Festival in 1989. The whistled intro became iconic, symbolizing the end of the Cold War.",
      "fun_fact_de": "[DE] Written after the Scorpions played the Moscow Music Peace Festival in 1989. The ...",
      "fun_fact_es": "[ES] Written after the Scorpions played the Moscow Music Peace Festival in 1989. The ...",
      "uri_apple_music": "applemusic://track/1438813154",
      "uri_youtube_music": "https://music.youtube.com/watch?v=n4RjJKxsamQ",
      "uri_tidal": "tidal://track/1894868"
    },
    {
      "year": 1981,
      "uri": "spotify:track:1bCMeYi91d4TH2Z5tJMW0c",
      "artist": "Phil Collins",
      "alt_artists": [
        "Genesis",
        "Peter Gabriel"
      ],
      "title": "In The Air Tonight",
      "chart_info": {
        "billboard_peak": 19,
        "uk_peak": 2,
        "weeks_on_chart": 16
      },
      "certifications": [
        "Gold (US)",
        "Silver (UK)"
      ],
      "awards": [],
      "fun_fact": "The famous drum fill was created using a gated reverb technique invented by accident. Urban legends about the song's meaning persist, though Phil says it's about his divorce.",
      "fun_fact_de": "[DE] The famous drum fill was created using a gated reverb technique invented by acci...",
      "fun_fact_es": "[ES] The famous drum fill was created using a gated reverb technique invented by acci...",
      "uri_apple_music": "applemusic://track/1076779225",
      "uri_youtube_music": "https://music.youtube.com/watch?v=YkADj0TPrJA",
      "uri_tidal": "tidal://track/99361661"
    },
    {
      "year": 1990,
      "uri": "spotify:track:1cX89LkWJoJPS8uJFpqkIp",
      "artist": "Alannah Myles",
      "alt_artists": [
        "Melissa Etheridge",
        "Joan Jett"
      ],
      "title": "Black Velvet",
      "chart_info": {
        "billboard_peak": 1,
        "uk_peak": 2,
        "weeks_on_chart": 18
      },
      "certifications": [
        "Platinum (US)",
        "Gold (UK)"
      ],
      "awards": [],
      "fun_fact": "Written as a tribute to Elvis Presley, the 'Black Velvet' refers to his dark, smooth voice. Alannah's husky vocals earned her a Grammy for Best Female Rock Vocal.",
      "fun_fact_de": "[DE] Written as a tribute to Elvis Presley, the 'Black Velvet' refers to his dark, sm...",
      "fun_fact_es": "[ES] Written as a tribute to Elvis Presley, the 'Black Velvet' refers to his dark, sm...",
      "uri_apple_music": "applemusic://track/1837530994",
      "uri_youtube_music": "https://music.youtube.com/watch?v=tT4d1LQy4es",
      "uri_tidal": "tidal://track/1408377"
    },
    {
      "year": 1985,
      "uri": "spotify:track:1m2INxep6LfNa25OEg5jZl",
      "artist": "Mötley Crüe",
      "alt_artists": [
        "Poison",
        "Ratt"
      ],
      "title": "Home Sweet Home",
      "chart_info": {
        "billboard_peak": 89,
        "uk_peak": 51,
        "weeks_on_chart": 10
      },
      "certifications": [
        "Gold (US)"
      ],
      "awards": [],
      "fun_fact": "Written by Nikki Sixx and Vince Neil about missing home while on tour. The piano-driven ballad proved hair metal bands could be vulnerable and became a concert staple.",
      "fun_fact_de": "[DE] Written by Nikki Sixx and Vince Neil about missing home while on tour. The piano...",
      "fun_fact_es": "[ES] Written by Nikki Sixx and Vince Neil about missing home while on tour. The piano...",
      "uri_apple_music": "applemusic://track/1606706533",
      "uri_youtube_music": "https://music.youtube.com/watch?v=Gmrh42foUsg",
      "uri_tidal": "tidal://track/1781742"
    },
    {
      "year": 2002,
      "uri": "spotify:track:1xIZonNhFX3kvYYBedx69u",
      "artist": "Christina Aguilera",
      "alt_artists": [
        "Britney Spears",
        "Pink"
      ],
      "title": "Beautiful",
      "chart_info": {
        "billboard_peak": 2,
        "uk_peak": 1,
        "weeks_on_chart": 20
      },
      "certifications": [
        "Platinum (US)",
        "Platinum (UK)"
      ],
      "awards": [],
      "fun_fact": "Written by Linda Perry, this became an anthem for self-acceptance. Christina's raw, emotional delivery made it a defining song of her career and won a Grammy.",
      "fun_fact_de": "[DE] Written by Linda Perry, this became an anthem for self-acceptance. Christina's r...",
      "fun_fact_es": "[ES] Written by Linda Perry, this became an anthem for self-acceptance. Christina's r...",
      "uri_apple_music": "applemusic://track/279647290",
      "uri_youtube_music": "https://music.youtube.com/watch?v=7kEwGXLdbZ8",
      "uri_tidal": "tidal://track/2918517"
    },
    {
      "year": 1984,
      "uri": "spotify:track:225xvV8r1yKMHErSWivnow",
      "artist": "Night Ranger",
      "alt_artists": [
        "Survivor",
        "38 Special"
      ],
      "title": "Sister Christian",
      "chart_info": {
        "billboard_peak": 5,
        "uk_peak": 91,
        "weeks_on_chart": 16
      },
      "certifications": [
        "Gold (US)"
      ],
      "awards": [],
      "fun_fact": "Written by drummer Kelly Keagy about his younger sister. The famous 'motoring' line was originally 'mothering' - the band changed it thinking Kelly was singing it wrong.",
      "fun_fact_de": "[DE] Written by drummer Kelly Keagy about his younger sister. The famous 'motoring' l...",
      "fun_fact_es": "[ES] Written by drummer Kelly Keagy about his younger sister. The famous 'motoring' l...",
      "uri_apple_music": "applemusic://track/1440648051",
      "uri_youtube_music": "https://music.youtube.com/watch?v=z92bmlcmyq0",
      "uri_tidal": "tidal://track/5128020"
    },
    {
      "year": 1983,
      "uri": "spotify:track:23NPGXlSaIqWzvxIRhM2oG",
      "artist": "Bonnie Tyler",
      "alt_artists": [
        "Cher",
        "Jennifer Rush"
      ],
      "title": "Total Eclipse of the Heart",
      "chart_info": {
        "billboard_peak": 1,
        "uk_peak": 1,
        "weeks_on_chart": 21
      },
      "certifications": [
        "2x Platinum (US)",
        "Platinum (UK)"
      ],
      "awards": [],
      "fun_fact": "Jim Steinman originally wrote this for a vampire musical, calling it 'Vampires in Love'. Bonnie Tyler's distinctive raspy voice came from a nodule surgery that went wrong.",
      "fun_fact_de": "[DE] Jim Steinman originally wrote this for a vampire musical, calling it 'Vampires i...",
      "fun_fact_es": "[ES] Jim Steinman originally wrote this for a vampire musical, calling it 'Vampires i...",
      "uri_apple_music": "applemusic://track/1504111288",
      "uri_youtube_music": "https://music.youtube.com/watch?v=lcOxhH8N3Bo",
      "uri_tidal": "tidal://track/304849"
    },
    {
      "year": 2004,
      "uri": "spotify:track:2Hw5F4S5TFmrpBoWXc2Awx",
      "artist": "Hoobastank",
      "alt_artists": [
        "Staind",
        "Puddle of Mudd"
      ],
      "title": "The Reason",
      "chart_info": {
        "billboard_peak": 2,
        "uk_peak": 12,
        "weeks_on_chart": 18
      },
      "certifications": [
        "Platinum (US)"
      ],
      "awards": [],
      "fun_fact": "Doug Robb wrote this after reflecting on mistakes in past relationships. It became the band's breakthrough hit and defined the mid-2000s rock ballad sound.",
      "fun_fact_de": "[DE] Doug Robb wrote this after reflecting on mistakes in past relationships. It beca...",
      "fun_fact_es": "[ES] Doug Robb wrote this after reflecting on mistakes in past relationships. It beca...",
      "uri_apple_music": "applemusic://track/1440769862",
      "uri_youtube_music": "https://music.youtube.com/watch?v=fV4DiAyExN0",
      "uri_tidal": "tidal://track/3081936"
    },
    {
      "year": 1985,
      "uri": "spotify:track:2IJzqbcbQZjcca53yGkX7t",
      "artist": "Marillion",
      "alt_artists": [
        "Genesis",
        "Pink Floyd"
      ],
      "title": "Kayleigh - Single Edit",
      "chart_info": {
        "billboard_peak": 74,
        "uk_peak": 2,
        "weeks_on_chart": 14
      },
      "certifications": [
        "Silver (UK)"
      ],
      "awards": [],
      "fun_fact": "Named after a real woman Fish (the vocalist) had a relationship with. The name Kayleigh saw a huge surge in popularity after this song, becoming a top baby name in the UK.",
      "fun_fact_de": "[DE] Named after a real woman Fish (the vocalist) had a relationship with. The name K...",
      "fun_fact_es": "[ES] Named after a real woman Fish (the vocalist) had a relationship with. The name K...",
      "uri_apple_music": "applemusic://track/726107942",
      "uri_youtube_music": "https://music.youtube.com/watch?v=FiM0JiE0h5I",
      "uri_tidal": "tidal://track/127195"
    },
    {
      "year": 1997,
      "uri": "spotify:track:2QHOopHJw2AfBJmagmyHF0",
      "artist": "Robbie Williams",
      "alt_artists": [
        "George Michael",
        "Take That"
      ],
      "title": "Angels",
      "chart_info": {
        "billboard_peak": 53,
        "uk_peak": 4,
        "weeks_on_chart": 16
      },
      "certifications": [
        "Gold (UK)"
      ],
      "awards": [],
      "fun_fact": "Co-written with Guy Chambers in just 25 minutes. It's been voted Britain's best song to be played at funerals and remains Robbie's signature song.",
      "fun_fact_de": "[DE] Co-written with Guy Chambers in just 25 minutes. It's been voted Britain's best ...",
      "fun_fact_es": "[ES] Co-written with Guy Chambers in just 25 minutes. It's been voted Britain's best ...",
      "uri_apple_music": "applemusic://track/725818406",
      "uri_youtube_music": "https://music.youtube.com/watch?v=luwAMFcc2f8",
      "uri_tidal": "tidal://track/73862558"
    },
    {
      "year": 1984,
      "uri": "spotify:track:2amzrvbxYiq8AxGntIiw5V",
      "artist": "The Cars",
      "alt_artists": [
        "Duran Duran",
        "Depeche Mode"
      ],
      "title": "Drive",
      "chart_info": {
        "billboard_peak": 3,
        "uk_peak": 4,
        "weeks_on_chart": 17
      },
      "certifications": [
        "Gold (US)",
        "Silver (UK)"
      ],
      "awards": [],
      "fun_fact": "Benjamin Orr sang lead on this emotional ballad. It gained renewed prominence when used in a Live Aid video about the Ethiopian famine, bringing viewers to tears.",
      "fun_fact_de": "[DE] Benjamin Orr sang lead on this emotional ballad. It gained renewed prominence wh...",
      "fun_fact_es": "[ES] Benjamin Orr sang lead on this emotional ballad. It gained renewed prominence wh...",
      "uri_apple_music": "applemusic://track/1088531479",
      "uri_youtube_music": "https://music.youtube.com/watch?v=xuZA6qiJVfU",
      "uri_tidal": "tidal://track/2987610"
    },
    {
      "year": 1985,
      "uri": "spotify:track:2eY1BRbRcK6SRb0rD90suw",
      "artist": "Jennifer Rush",
      "alt_artists": [
        "Céline Dion",
        "Bonnie Tyler"
      ],
      "title": "The Power of Love",
      "chart_info": {
        "billboard_peak": 57,
        "uk_peak": 1,
        "weeks_on_chart": 16
      },
      "certifications": [
        "Platinum (UK)"
      ],
      "awards": [],
      "fun_fact": "Spent 5 weeks at #1 in the UK and became the first song by a female American artist to sell a million copies in the UK. Later covered by Céline Dion.",
      "fun_fact_de": "[DE] Spent 5 weeks at #1 in the UK and became the first song by a female American art...",
      "fun_fact_es": "[ES] Spent 5 weeks at #1 in the UK and became the first song by a female American art...",
      "uri_apple_music": "applemusic://track/209433632",
      "uri_youtube_music": "https://music.youtube.com/watch?v=b_zHQ6kFuQ0",
      "uri_tidal": "tidal://track/31849290"
    },
    {
      "year": 1994,
      "uri": "spotify:track:2hMF7H2dO3oMz1WwIQnQw1",
      "artist": "Bon Jovi",
      "alt_artists": [
        "Def Leppard",
        "Poison"
      ],
      "title": "Always",
      "chart_info": {
        "billboard_peak": 4,
        "uk_peak": 2,
        "weeks_on_chart": 20
      },
      "certifications": [
        "2x Platinum (US)",
        "Platinum (UK)"
      ],
      "awards": [],
      "fun_fact": "Originally written for the film Romeo Is Bleeding but was rejected. It became one of Bon Jovi's biggest hits and Jon's personal favorite ballad.",
      "fun_fact_de": "[DE] Originally written for the film Romeo Is Bleeding but was rejected. It became on...",
      "fun_fact_es": "[ES] Originally written for the film Romeo Is Bleeding but was rejected. It became on...",
      "uri_apple_music": "applemusic://track/1423285054",
      "uri_youtube_music": "https://music.youtube.com/watch?v=9BMwcO6_hyA",
      "uri_tidal": "tidal://track/65556726"
    },
    {
      "year": 1989,
      "uri": "spotify:track:2kDH08boXJyhKMl5hnZbrE",
      "artist": "The Bangles",
      "alt_artists": [
        "The Go-Go's",
        "Heart"
      ],
      "title": "Eternal Flame",
      "chart_info": {
        "billboard_peak": 1,
        "uk_peak": 1,
        "weeks_on_chart": 19
      },
      "certifications": [
        "Gold (US)",
        "Gold (UK)"
      ],
      "awards": [],
      "fun_fact": "Written after Susanna Hoffs visited the eternal flame at Elvis Presley's grave. Billy Steinberg co-wrote it after dreaming about an eternal flame.",
      "fun_fact_de": "[DE] Written after Susanna Hoffs visited the eternal flame at Elvis Presley's grave. ...",
      "fun_fact_es": "[ES] Written after Susanna Hoffs visited the eternal flame at Elvis Presley's grave. ...",
      "uri_apple_music": "applemusic://track/390617130",
      "uri_youtube_music": "https://music.youtube.com/watch?v=PSoOFn3wQV4",
      "uri_tidal": "tidal://track/546775"
    },
    {
      "year": 1988,
      "uri": "spotify:track:2owpdFd1qqSSe6TEzceXpc",
      "artist": "Cinderella",
      "alt_artists": [
        "Poison",
        "Warrant"
      ],
      "title": "Don't Know What You Got (Till It's Gone)",
      "chart_info": {
        "billboard_peak": 12,
        "uk_peak": 54,
        "weeks_on_chart": 15
      },
      "certifications": [
        "Gold (US)"
      ],
      "awards": [],
      "fun_fact": "Tom Keifer wrote this about a past relationship. The piano-driven ballad showed a different side of the glam metal band and became their signature song.",
      "fun_fact_de": "[DE] Tom Keifer wrote this about a past relationship. The piano-driven ballad showed ...",
      "fun_fact_es": "[ES] Tom Keifer wrote this about a past relationship. The piano-driven ballad showed ...",
      "uri_apple_music": "applemusic://track/1434883426",
      "uri_youtube_music": "https://music.youtube.com/watch?v=i28UEoLXVFQ",
      "uri_tidal": "tidal://track/661020"
    },
    {
      "year": 1989,
      "uri": "spotify:track:2tVinls1mEvkUtkrGiA1K9",
      "artist": "Richard Marx",
      "alt_artists": [
        "Bryan Adams",
        "Michael Bolton"
      ],
      "title": "Right Here Waiting",
      "chart_info": {
        "billboard_peak": 1,
        "uk_peak": 2,
        "weeks_on_chart": 19
      },
      "certifications": [
        "Platinum (US)",
        "Gold (UK)"
      ],
      "awards": [],
      "fun_fact": "Written for his wife Cynthia Rhodes while she was filming a movie in South Africa and he couldn't visit due to apartheid travel restrictions.",
      "fun_fact_de": "[DE] Written for his wife Cynthia Rhodes while she was filming a movie in South Afric...",
      "fun_fact_es": "[ES] Written for his wife Cynthia Rhodes while she was filming a movie in South Afric...",
      "uri_apple_music": "applemusic://track/725843719",
      "uri_youtube_music": "https://music.youtube.com/watch?v=S_E2EHVxNAE",
      "uri_tidal": "tidal://track/11668522"
    },
    {
      "year": 2003,
      "uri": "spotify:track:2vEQ9zBiwbAVXzS2SOxodY",
      "artist": "3 Doors Down",
      "alt_artists": [
        "Nickelback",
        "Creed"
      ],
      "title": "Here Without You",
      "chart_info": {
        "billboard_peak": 5,
        "uk_peak": 23,
        "weeks_on_chart": 17
      },
      "certifications": [
        "Platinum (US)"
      ],
      "awards": [],
      "fun_fact": "Written by Brad Arnold in just 15 minutes while thinking about being away from home. The military adopted it as an anthem for troops deployed overseas.",
      "fun_fact_de": "[DE] Written by Brad Arnold in just 15 minutes while thinking about being away from h...",
      "fun_fact_es": "[ES] Written by Brad Arnold in just 15 minutes while thinking about being away from h...",
      "uri_apple_music": "applemusic://track/1440831121",
      "uri_youtube_music": "https://music.youtube.com/watch?v=kPBzTxZQG5Q",
      "uri_tidal": "tidal://track/100578065"
    },
    {
      "year": 1987,
      "uri": "spotify:track:39J10NL0mFTAdJbapoo2rC",
      "artist": "Cutting Crew",
      "alt_artists": [
        "Mr. Mister",
        "A Flock of Seagulls"
      ],
      "title": "(I Just) Died In Your Arms",
      "chart_info": {
        "billboard_peak": 1,
        "uk_peak": 4,
        "weeks_on_chart": 17
      },
      "certifications": [
        "Platinum (US)",
        "Silver (UK)"
      ],
      "awards": [],
      "fun_fact": "Nick Van Eede wrote this based on the French phrase 'la petite mort' (the little death), a metaphor for orgasm. It's Cutting Crew's only major hit.",
      "fun_fact_de": "[DE] Nick Van Eede wrote this based on the French phrase 'la petite mort' (the little...",
      "fun_fact_es": "[ES] Nick Van Eede wrote this based on the French phrase 'la petite mort' (the little...",
      "uri_apple_music": "applemusic://track/1795082893",
      "uri_youtube_music": "https://music.youtube.com/watch?v=6dOwHzCHfgA",
      "uri_tidal": "tidal://track/530"
    },
    {
      "year": 1994,
      "uri": "spotify:track:3HKthdb7Ejnydb74BvmQW0",
      "artist": "Mariah Carey",
      "alt_artists": [
        "Whitney Houston",
        "Céline Dion"
      ],
      "title": "Without You",
      "chart_info": {
        "billboard_peak": 3,
        "uk_peak": 1,
        "weeks_on_chart": 18
      },
      "certifications": [
        "Platinum (US)",
        "Platinum (UK)"
      ],
      "awards": [],
      "fun_fact": "Originally by Badfinger in 1970, later a huge hit for Harry Nilsson. Mariah's powerful version showcased her incredible whistle register and became definitive.",
      "fun_fact_de": "[DE] Originally by Badfinger in 1970, later a huge hit for Harry Nilsson. Mariah's po...",
      "fun_fact_es": "[ES] Originally by Badfinger in 1970, later a huge hit for Harry Nilsson. Mariah's po...",
      "uri_apple_music": "applemusic://track/190174947",
      "uri_youtube_music": "https://music.youtube.com/watch?v=Hat1Hc9SNwE",
      "uri_tidal": "tidal://track/2845116"
    },
    {
      "year": 1975,
      "uri": "spotify:track:3S3dZXxNGghLtOqehzHtii",
      "artist": "Nazareth",
      "alt_artists": [
        "Thin Lizzy",
        "UFO"
      ],
      "title": "Love Hurts - Live",
      "chart_info": {
        "billboard_peak": 8,
        "uk_peak": 43,
        "weeks_on_chart": 14
      },
      "certifications": [
        "Gold (US)"
      ],
      "awards": [],
      "fun_fact": "Written by Boudleaux Bryant in 1960 and first recorded by The Everly Brothers. Nazareth's hard rock version is the most famous, though they almost didn't release it.",
      "fun_fact_de": "[DE] Written by Boudleaux Bryant in 1960 and first recorded by The Everly Brothers. N...",
      "fun_fact_es": "[ES] Written by Boudleaux Bryant in 1960 and first recorded by The Everly Brothers. N...",
      "uri_apple_music": "applemusic://track/1440632340",
      "uri_youtube_music": "https://music.youtube.com/watch?v=vOn0z0IRVN8",
      "uri_tidal": "tidal://track/1195363"
    },
    {
      "year": 1988,
      "uri": "spotify:track:3TCauNPqFiniaYHBvEVoHG",
      "artist": "INXS",
      "alt_artists": [
        "Duran Duran",
        "Simple Minds"
      ],
      "title": "Never Tear Us Apart",
      "chart_info": {
        "billboard_peak": 7,
        "uk_peak": 24,
        "weeks_on_chart": 15
      },
      "certifications": [
        "Gold (US)"
      ],
      "awards": [],
      "fun_fact": "Michael Hutchence and Andrew Farriss wrote this orchestral rock ballad. The strings were arranged by the legendary Nick Launay, giving it an epic, cinematic quality.",
      "fun_fact_de": "[DE] Michael Hutchence and Andrew Farriss wrote this orchestral rock ballad. The stri...",
      "fun_fact_es": "[ES] Michael Hutchence and Andrew Farriss wrote this orchestral rock ballad. The stri...",
      "uri_apple_music": "applemusic://track/828779772",
      "uri_youtube_music": "https://music.youtube.com/watch?v=AIBv2GEnXlc",
      "uri_tidal": "tidal://track/48933"
    },
    {
      "year": 1992,
      "uri": "spotify:track:3Y8WRvVlQHMvtBwaV4TGlJ",
      "artist": "Mr. Big",
      "alt_artists": [
        "Extreme",
        "Winger"
      ],
      "title": "To Be With You",
      "chart_info": {
        "billboard_peak": 1,
        "uk_peak": 3,
        "weeks_on_chart": 19
      },
      "certifications": [
        "Platinum (US)",
        "Gold (UK)"
      ],
      "awards": [],
      "fun_fact": "Written in 1989 but not released until the Right Man album. Eric Martin sang lead on this acoustic ballad, which topped charts in 15 countries simultaneously.",
      "fun_fact_de": "[DE] Written in 1989 but not released until the Right Man album. Eric Martin sang lea...",
      "fun_fact_es": "[ES] Written in 1989 but not released until the Right Man album. Eric Martin sang lea...",
      "uri_apple_music": "applemusic://track/1270576306",
      "uri_youtube_music": "https://music.youtube.com/watch?v=L6-uJLteKek",
      "uri_tidal": "tidal://track/579992"
    },
    {
      "year": 1989,
      "uri": "spotify:track:3ZFwuJwUpIl0GeXsvF1ELf",
      "artist": "Cher",
      "alt_artists": [
        "Madonna",
        "Tina Turner"
      ],
      "title": "If I Could Turn Back Time",
      "chart_info": {
        "billboard_peak": 3,
        "uk_peak": 6,
        "weeks_on_chart": 16
      },
      "certifications": [
        "Gold (US)",
        "Silver (UK)"
      ],
      "awards": [],
      "fun_fact": "Written by Diane Warren. The controversial music video was filmed on the USS Missouri with Cher wearing a revealing outfit, causing some networks to ban it.",
      "fun_fact_de": "[DE] Written by Diane Warren. The controversial music video was filmed on the USS Mis...",
      "fun_fact_es": "[ES] Written by Diane Warren. The controversial music video was filmed on the USS Mis...",
      "uri_apple_music": "applemusic://track/1571969050",
      "uri_youtube_music": "https://music.youtube.com/watch?v=9n3A_-HRFfc",
      "uri_tidal": "tidal://track/196435453"
    },
    {
      "year": 1988,
      "uri": "spotify:track:3fOODM4MYSBmCZoSOSyOjP",
      "artist": "Def Leppard",
      "alt_artists": [
        "Bon Jovi",
        "Whitesnake"
      ],
      "title": "Love Bites",
      "chart_info": {
        "billboard_peak": 1,
        "uk_peak": 11,
        "weeks_on_chart": 18
      },
      "certifications": [
        "Platinum (US)"
      ],
      "awards": [],
      "fun_fact": "Def Leppard's only #1 hit in the US. The song took 4 years to complete as part of the Hysteria album, which was plagued by drummer Rick Allen's accident.",
      "fun_fact_de": "[DE] Def Leppard's only #1 hit in the US. The song took 4 years to complete as part o...",
      "fun_fact_es": "[ES] Def Leppard's only #1 hit in the US. The song took 4 years to complete as part o...",
      "uri_apple_music": "applemusic://track/1643512302",
      "uri_youtube_music": "https://music.youtube.com/watch?v=W4XiSFyYRE8",
      "uri_tidal": "tidal://track/170798223"
    },
    {
      "year": 2000,
      "uri": "spotify:track:3gqGgN7mCV52NkNWgAcY9f",
      "artist": "Lenny Kravitz",
      "alt_artists": [
        "Prince",
        "Hendrix"
      ],
      "title": "Again",
      "chart_info": {
        "billboard_peak": 4,
        "uk_peak": 14,
        "weeks_on_chart": 15
      },
      "certifications": [
        "Gold (US)"
      ],
      "awards": [],
      "fun_fact": "Written and produced entirely by Lenny Kravitz in his home studio. It showed a more vulnerable side and became one of his most-played songs on adult contemporary radio.",
      "fun_fact_de": "[DE] Written and produced entirely by Lenny Kravitz in his home studio. It showed a m...",
      "fun_fact_es": "[ES] Written and produced entirely by Lenny Kravitz in his home studio. It showed a m...",
      "uri_apple_music": "",
      "uri_youtube_music": "https://music.youtube.com/watch?v=eW2qlKa6oHw",
      "uri_tidal": "tidal://track/77662157"
    },
    {
      "year": 1980,
      "uri": "spotify:track:3pyTksNccLM1jRvzQ4zTke",
      "artist": "Air Supply",
      "alt_artists": [
        "Chicago",
        "Bread"
      ],
      "title": "All Out of Love",
      "chart_info": {
        "billboard_peak": 2,
        "uk_peak": 11,
        "weeks_on_chart": 18
      },
      "certifications": [
        "Platinum (US)"
      ],
      "awards": [],
      "fun_fact": "Graham Russell wrote this in 10 minutes. The song's distinctive keyboard riff became an 80s soft rock signature and made Air Supply international stars.",
      "fun_fact_de": "[DE] Graham Russell wrote this in 10 minutes. The song's distinctive keyboard riff be...",
      "fun_fact_es": "[ES] Graham Russell wrote this in 10 minutes. The song's distinctive keyboard riff be...",
      "uri_apple_music": "applemusic://track/1445843398",
      "uri_youtube_music": "https://music.youtube.com/watch?v=JWdZEumNRmI",
      "uri_tidal": "tidal://track/7935352"
    },
    {
      "year": 2001,
      "uri": "spotify:track:3wXHoN9TNwGYBZFNEjfH0U",
      "artist": "Chad Kroeger",
      "alt_artists": [
        "Nickelback",
        "Theory of a Deadman"
      ],
      "title": "Hero (feat. Josey Scott)",
      "chart_info": {
        "billboard_peak": 0,
        "uk_peak": 0,
        "weeks_on_chart": 0
      },
      "certifications": [],
      "awards": [],
      "fun_fact": "A classic power ballad by Chad Kroeger.",
      "fun_fact_de": "",
      "fun_fact_es": "",
      "uri_apple_music": "applemusic://track/216661494",
      "uri_youtube_music": "https://music.youtube.com/watch?v=Vuw8SRDNEDI",
      "uri_tidal": "tidal://track/1870901"
    },
    {
      "year": 1982,
      "uri": "spotify:track:3wfujdbamR3Z46F4xav7LM",
      "artist": "Joe Cocker",
      "alt_artists": [
        "Rod Stewart",
        "Eric Clapton"
      ],
      "title": "Up Where We Belong",
      "chart_info": {
        "billboard_peak": 1,
        "uk_peak": 7,
        "weeks_on_chart": 17
      },
      "certifications": [
        "Gold (US)"
      ],
      "awards": [],
      "fun_fact": "Written for An Officer and a Gentleman, it won the Oscar for Best Original Song. Joe Cocker and Jennifer Warnes had to record their parts separately due to scheduling conflicts.",
      "fun_fact_de": "[DE] Written for An Officer and a Gentleman, it won the Oscar for Best Original Song....",
      "fun_fact_es": "[ES] Written for An Officer and a Gentleman, it won the Oscar for Best Original Song....",
      "uri_apple_music": "applemusic://track/1088531479",
      "uri_youtube_music": "https://music.youtube.com/watch?v=bjrOcrisGyI",
      "uri_tidal": "tidal://track/3267925"
    },
    {
      "year": 1991,
      "uri": "spotify:track:3wsz8TvMB8hBwIGZasfwoe",
      "artist": "Marc Cohn",
      "alt_artists": [
        "James Taylor",
        "Jackson Browne"
      ],
      "title": "Walking in Memphis",
      "chart_info": {
        "billboard_peak": 13,
        "uk_peak": 22,
        "weeks_on_chart": 14
      },
      "certifications": [
        "Gold (US)"
      ],
      "awards": [],
      "fun_fact": "Based on Marc Cohn's first trip to Memphis, including his visit to Graceland. He was so moved by the experience that he wrote the song in one night.",
      "fun_fact_de": "[DE] Based on Marc Cohn's first trip to Memphis, including his visit to Graceland. He...",
      "fun_fact_es": "[ES] Based on Marc Cohn's first trip to Memphis, including his visit to Graceland. He...",
      "uri_apple_music": "applemusic://track/1440648051",
      "uri_youtube_music": "https://music.youtube.com/watch?v=PgRafRp-P-o",
      "uri_tidal": "tidal://track/3238202"
    },
    {
      "year": 1990,
      "uri": "spotify:track:4CDoeHIz44HzXq3j6LkZq6",
      "artist": "Damn Yankees",
      "alt_artists": [
        "Ted Nugent",
        "Styx"
      ],
      "title": "High Enough",
      "chart_info": {
        "billboard_peak": 3,
        "uk_peak": 37,
        "weeks_on_chart": 16
      },
      "certifications": [
        "Gold (US)"
      ],
      "awards": [],
      "fun_fact": "Written by Tommy Shaw and Jack Blades. The supergroup featured Ted Nugent, and this power ballad proved they could do more than hard-driving rock.",
      "fun_fact_de": "[DE] Written by Tommy Shaw and Jack Blades. The supergroup featured Ted Nugent, and t...",
      "fun_fact_es": "[ES] Written by Tommy Shaw and Jack Blades. The supergroup featured Ted Nugent, and t...",
      "uri_apple_music": "applemusic://track/321975428",
      "uri_youtube_music": "https://music.youtube.com/watch?v=l_uh8XjgLTE",
      "uri_tidal": "tidal://track/31849195"
    },
    {
      "year": 1988,
      "uri": "spotify:track:4E0lSJ6c5unoku9UIZoJSl",
      "artist": "Whitney Houston",
      "alt_artists": [
        "Mariah Carey",
        "Céline Dion"
      ],
      "title": "One Moment in Time",
      "chart_info": {
        "billboard_peak": 5,
        "uk_peak": 1,
        "weeks_on_chart": 15
      },
      "certifications": [
        "Gold (US)",
        "Gold (UK)"
      ],
      "awards": [],
      "fun_fact": "Written for the 1988 Seoul Olympics. Albert Hammond and John Bettis crafted it specifically for Whitney's voice, and it became an anthem for athletes worldwide.",
      "fun_fact_de": "[DE] Written for the 1988 Seoul Olympics. Albert Hammond and John Bettis crafted it s...",
      "fun_fact_es": "[ES] Written for the 1988 Seoul Olympics. Albert Hammond and John Bettis crafted it s...",
      "uri_apple_music": "applemusic://track/158580601",
      "uri_youtube_music": "https://music.youtube.com/watch?v=96aAx0kxVSA",
      "uri_tidal": "tidal://track/1273648"
    },
    {
      "year": 1976,
      "uri": "spotify:track:4LFwNJWoj74Yd71fIr1W8x",
      "artist": "Queen",
      "alt_artists": [
        "David Bowie",
        "Elton John"
      ],
      "title": "Somebody To Love - Remastered 2011",
      "chart_info": {
        "billboard_peak": 13,
        "uk_peak": 2,
        "weeks_on_chart": 14
      },
      "certifications": [
        "Gold (UK)"
      ],
      "awards": [],
      "fun_fact": "Freddie Mercury was inspired by gospel music and Aretha Franklin. The harmonies required over 100 vocal overdubs to achieve the choir effect.",
      "fun_fact_de": "[DE] Freddie Mercury was inspired by gospel music and Aretha Franklin. The harmonies ...",
      "fun_fact_es": "[ES] Freddie Mercury was inspired by gospel music and Aretha Franklin. The harmonies ...",
      "uri_apple_music": "applemusic://track/1440651012",
      "uri_youtube_music": "https://music.youtube.com/watch?v=kijpcUv-b8M",
      "uri_tidal": "tidal://track/158013"
    },
    {
      "year": 1992,
      "uri": "spotify:track:4RpSnz7bmzI8fFNnLSiNB7",
      "artist": "4 Non Blondes",
      "alt_artists": [
        "Counting Crows",
        "Spin Doctors"
      ],
      "title": "What's Up? - Edit",
      "chart_info": {
        "billboard_peak": 0,
        "uk_peak": 0,
        "weeks_on_chart": 0
      },
      "certifications": [],
      "awards": [],
      "fun_fact": "A classic power ballad by 4 Non Blondes.",
      "fun_fact_de": "",
      "fun_fact_es": "",
      "uri_apple_music": "applemusic://track/1440902348",
      "uri_youtube_music": "https://music.youtube.com/watch?v=6NXnxTNIWkc",
      "uri_tidal": "tidal://track/21844149"
    },
    {
      "year": 2005,
      "uri": "spotify:track:4UrgDocbHywDZv2f3mBhCq",
      "artist": "Backstreet Boys",
      "alt_artists": [
        "NSYNC",
        "98 Degrees"
      ],
      "title": "Incomplete",
      "chart_info": {
        "billboard_peak": 13,
        "uk_peak": 8,
        "weeks_on_chart": 14
      },
      "certifications": [
        "Gold (US)"
      ],
      "awards": [],
      "fun_fact": "The comeback single after a 3-year hiatus. Written by Backstreet Boys with Dan Muckala, it addressed their time apart and emotional journey.",
      "fun_fact_de": "[DE] The comeback single after a 3-year hiatus. Written by Backstreet Boys with Dan M...",
      "fun_fact_es": "[ES] The comeback single after a 3-year hiatus. Written by Backstreet Boys with Dan M...",
      "uri_apple_music": "applemusic://track/724203469",
      "uri_youtube_music": "https://music.youtube.com/watch?v=WVe80iZtlYU",
      "uri_tidal": "tidal://track/135463"
    },
    {
      "year": 1984,
      "uri": "spotify:track:4cBjhKOEXr66AlBtyyPrPe",
      "artist": "Prince",
      "alt_artists": [
        "Michael Jackson",
        "Rick James"
      ],
      "title": "Purple Rain",
      "chart_info": {
        "billboard_peak": 2,
        "uk_peak": 8,
        "weeks_on_chart": 18
      },
      "certifications": [
        "2x Platinum (US)",
        "Gold (UK)"
      ],
      "awards": [],
      "fun_fact": "The epic 8-minute version was recorded live in one take at First Avenue in Minneapolis. Prince wrote it about the end of the world and seeking redemption through faith.",
      "fun_fact_de": "[DE] The epic 8-minute version was recorded live in one take at First Avenue in Minne...",
      "fun_fact_es": "[ES] The epic 8-minute version was recorded live in one take at First Avenue in Minne...",
      "uri_apple_music": "applemusic://track/1445835626",
      "uri_youtube_music": "https://music.youtube.com/watch?v=TvnYmWpD_T8",
      "uri_tidal": "tidal://track/1568613"
    },
    {
      "year": 1989,
      "uri": "spotify:track:4n9e8Nx2FijSDVoumQwXPW",
      "artist": "Alice Cooper",
      "alt_artists": [
        "KISS",
        "Ozzy Osbourne"
      ],
      "title": "Poison",
      "chart_info": {
        "billboard_peak": 7,
        "uk_peak": 2,
        "weeks_on_chart": 15
      },
      "certifications": [
        "Gold (US)",
        "Silver (UK)"
      ],
      "awards": [],
      "fun_fact": "Written by Desmond Child and marked Alice Cooper's commercial comeback. The song's theatrical nature fit perfectly with his horror-rock persona.",
      "fun_fact_de": "[DE] Written by Desmond Child and marked Alice Cooper's commercial comeback. The song...",
      "fun_fact_es": "[ES] Written by Desmond Child and marked Alice Cooper's commercial comeback. The song...",
      "uri_apple_music": "applemusic://track/193014297",
      "uri_youtube_music": "https://music.youtube.com/watch?v=Qq4j1LtCdww",
      "uri_tidal": "tidal://track/113471911"
    },
    {
      "year": 1990,
      "uri": "spotify:track:4npQqHOi5Zxxyw1oarSivu",
      "artist": "Warrant",
      "alt_artists": [
        "Poison",
        "Cinderella"
      ],
      "title": "Sometimes She Cries",
      "chart_info": {
        "billboard_peak": 20,
        "uk_peak": 59,
        "weeks_on_chart": 12
      },
      "certifications": [],
      "awards": [],
      "fun_fact": "Jani Lane wrote this ballad showcasing Warrant's softer side. It became an MTV staple and proved the band could deliver emotional depth beyond party anthems.",
      "fun_fact_de": "[DE] Jani Lane wrote this ballad showcasing Warrant's softer side. It became an MTV s...",
      "fun_fact_es": "[ES] Jani Lane wrote this ballad showcasing Warrant's softer side. It became an MTV s...",
      "uri_apple_music": "applemusic://track/1217902077",
      "uri_youtube_music": "https://music.youtube.com/watch?v=DAX20LoVgxE",
      "uri_tidal": "tidal://track/71770978"
    },
    {
      "year": 1983,
      "uri": "spotify:track:4rcHWl68ai6KvpXlc8vbnE",
      "artist": "Pat Benatar",
      "alt_artists": [
        "Heart",
        "Joan Jett"
      ],
      "title": "Love Is A Battlefield - Remastered 2005",
      "chart_info": {
        "billboard_peak": 5,
        "uk_peak": 17,
        "weeks_on_chart": 16
      },
      "certifications": [
        "Gold (US)"
      ],
      "awards": [],
      "fun_fact": "Features one of MTV's first narrative music videos with dance choreography. Pat Benatar was initially hesitant about the theatrical video concept.",
      "fun_fact_de": "[DE] Features one of MTV's first narrative music videos with dance choreography. Pat ...",
      "fun_fact_es": "[ES] Features one of MTV's first narrative music videos with dance choreography. Pat ...",
      "uri_apple_music": "applemusic://track/447759252",
      "uri_youtube_music": "https://music.youtube.com/watch?v=IGVZOLV9SPo",
      "uri_tidal": "tidal://track/7204760"
    },
    {
      "year": 1990,
      "uri": "spotify:track:4zpWGC5MmGN6zX4J9XV8Gv",
      "artist": "Bad Company",
      "alt_artists": [
        "Free",
        "Led Zeppelin"
      ],
      "title": "Feel Like Makin' Love (Remastered Album Version)",
      "chart_info": {
        "billboard_peak": 0,
        "uk_peak": 0,
        "weeks_on_chart": 0
      },
      "certifications": [],
      "awards": [],
      "fun_fact": "A classic power ballad by Bad Company.",
      "fun_fact_de": "",
      "fun_fact_es": "",
      "uri_apple_music": "applemusic://track/1440784502",
      "uri_youtube_music": "https://music.youtube.com/watch?v=OEPvv9pjIoQ",
      "uri_tidal": "tidal://track/1110429"
    },
    {
      "year": 1990,
      "uri": "spotify:track:53968oKecrFxkErocab2Al",
      "artist": "Tina Turner",
      "alt_artists": [
        "Cher",
        "Whitney Houston"
      ],
      "title": "We Don't Need Another Hero (Thunderdome)",
      "chart_info": {
        "billboard_peak": 0,
        "uk_peak": 0,
        "weeks_on_chart": 0
      },
      "certifications": [],
      "awards": [],
      "fun_fact": "A classic power ballad by Tina Turner.",
      "fun_fact_de": "",
      "fun_fact_es": "",
      "uri_apple_music": "applemusic://track/1644730834",
      "uri_youtube_music": "https://music.youtube.com/watch?v=HLBXAs2LO8k",
      "uri_tidal": "tidal://track/629061"
    },
    {
      "year": 1991,
      "uri": "spotify:track:54X78diSLoUDI3joC2bjMz",
      "artist": "Queensrÿche",
      "alt_artists": [
        "Dream Theater",
        "Fates Warning"
      ],
      "title": "Silent Lucidity - Remastered 2000",
      "chart_info": {
        "billboard_peak": 9,
        "uk_peak": 18,
        "weeks_on_chart": 15
      },
      "certifications": [
        "Gold (US)"
      ],
      "awards": [],
      "fun_fact": "Written about lucid dreaming by Chris DeGarmo. The orchestral arrangement was unusual for a progressive metal band and earned them mainstream success.",
      "fun_fact_de": "[DE] Written about lucid dreaming by Chris DeGarmo. The orchestral arrangement was un...",
      "fun_fact_es": "[ES] Written about lucid dreaming by Chris DeGarmo. The orchestral arrangement was un...",
      "uri_apple_music": "applemusic://track/723525006",
      "uri_youtube_music": "https://music.youtube.com/watch?v=jhat-xUQ6dw",
      "uri_tidal": "tidal://track/691735"
    },
    {
      "year": 1984,
      "uri": "spotify:track:5D6rk7Zr7FRy5m2fDte5fp",
      "artist": "John Waite",
      "alt_artists": [
        "The Babys",
        "Rick Springfield"
      ],
      "title": "Missing You",
      "chart_info": {
        "billboard_peak": 1,
        "uk_peak": 9,
        "weeks_on_chart": 18
      },
      "certifications": [
        "Gold (US)"
      ],
      "awards": [],
      "fun_fact": "Written about the denial stage of a breakup. The ironic lyrics 'I ain't missing you' became the song's emotional hook as John Waite's voice cracks with emotion.",
      "fun_fact_de": "[DE] Written about the denial stage of a breakup. The ironic lyrics 'I ain't missing ...",
      "fun_fact_es": "[ES] Written about the denial stage of a breakup. The ironic lyrics 'I ain't missing ...",
      "uri_apple_music": "applemusic://track/716357681",
      "uri_youtube_music": "https://music.youtube.com/watch?v=k9e157Ner90",
      "uri_tidal": "tidal://track/348192"
    },
    {
      "year": 1990,
      "uri": "spotify:track:5EcQ53R86rMZ5WnfbVvQEh",
      "artist": "Thunder",
      "alt_artists": [
        "Whitesnake",
        "Def Leppard"
      ],
      "title": "Love Walked In",
      "chart_info": {
        "billboard_peak": 0,
        "uk_peak": 21,
        "weeks_on_chart": 10
      },
      "certifications": [],
      "awards": [],
      "fun_fact": "British rock band Thunder's breakthrough hit. Danny Bowes' soulful vocals and Luke Morley's songwriting showed they could compete with American arena rock bands.",
      "fun_fact_de": "[DE] British rock band Thunder's breakthrough hit. Danny Bowes' soulful vocals and Lu...",
      "fun_fact_es": "[ES] British rock band Thunder's breakthrough hit. Danny Bowes' soulful vocals and Lu...",
      "uri_apple_music": "applemusic://track/723425523",
      "uri_youtube_music": "https://music.youtube.com/watch?v=-IWAOPi4VCc",
      "uri_tidal": "tidal://track/4785383"
    },
    {
      "year": 1987,
      "uri": "spotify:track:5MoDQWMDMaAGDEiWsJfeCi",
      "artist": "Starship",
      "alt_artists": [
        "Heart",
        "Journey"
      ],
      "title": "Nothing's Gonna Stop Us Now",
      "chart_info": {
        "billboard_peak": 1,
        "uk_peak": 1,
        "weeks_on_chart": 19
      },
      "certifications": [
        "Platinum (US)",
        "Gold (UK)"
      ],
      "awards": [],
      "fun_fact": "Written for the film Mannequin. It became Starship's second and final #1 hit, showcasing the band's transition from rock to pure pop.",
      "fun_fact_de": "[DE] Written for the film Mannequin. It became Starship's second and final #1 hit, sh...",
      "fun_fact_es": "[ES] Written for the film Mannequin. It became Starship's second and final #1 hit, sh...",
      "uri_apple_music": "applemusic://track/1758972763",
      "uri_youtube_music": "https://music.youtube.com/watch?v=3wxyN3z9PL4",
      "uri_tidal": "tidal://track/2811812"
    },
    {
      "year": 1992,
      "uri": "spotify:track:5NoUgO4Kr93QymQGQlBC7b",
      "artist": "Red Hot Chili Peppers",
      "alt_artists": [
        "Pearl Jam",
        "Jane's Addiction"
      ],
      "title": "Under the Bridge",
      "chart_info": {
        "billboard_peak": 2,
        "uk_peak": 13,
        "weeks_on_chart": 16
      },
      "certifications": [
        "Platinum (US)",
        "Silver (UK)"
      ],
      "awards": [],
      "fun_fact": "Anthony Kiedis wrote this about his loneliness and past drug use in Los Angeles. Producer Rick Rubin found the poem and convinced him to make it a song.",
      "fun_fact_de": "[DE] Anthony Kiedis wrote this about his loneliness and past drug use in Los Angeles....",
      "fun_fact_es": "[ES] Anthony Kiedis wrote this about his loneliness and past drug use in Los Angeles....",
      "uri_apple_music": "applemusic://track/948460560",
      "uri_youtube_music": "https://music.youtube.com/watch?v=GLvohMXgcBo",
      "uri_tidal": "tidal://track/1105825"
    },
    {
      "year": 1998,
      "uri": "spotify:track:5WwqdeavrQrbeAMDxGawse",
      "artist": "The Goo Goo Dolls",
      "alt_artists": [
        "Matchbox Twenty",
        "Counting Crows"
      ],
      "title": "Iris",
      "chart_info": {
        "billboard_peak": 9,
        "uk_peak": 26,
        "weeks_on_chart": 18
      },
      "certifications": [
        "2x Platinum (US)",
        "Gold (UK)"
      ],
      "awards": [],
      "fun_fact": "Written for the City of Angels soundtrack. John Rzeznik used a unique open tuning that he's used in many songs since. It spent 18 weeks at #1 on the Hot 100 Airplay chart.",
      "fun_fact_de": "[DE] Written for the City of Angels soundtrack. John Rzeznik used a unique open tunin...",
      "fun_fact_es": "[ES] Written for the City of Angels soundtrack. John Rzeznik used a unique open tunin...",
      "uri_apple_music": "applemusic://track/1109658204",
      "uri_youtube_music": "https://music.youtube.com/watch?v=NdYWuo9OFAw",
      "uri_tidal": "tidal://track/544229"
    },
    {
      "year": 1984,
      "uri": "spotify:track:5fgkjhICZnqFctrV0AyuQD",
      "artist": "Billy Idol",
      "alt_artists": [
        "Adam Ant",
        "Duran Duran"
      ],
      "title": "Eyes Without A Face",
      "chart_info": {
        "billboard_peak": 4,
        "uk_peak": 18,
        "weeks_on_chart": 16
      },
      "certifications": [
        "Gold (US)"
      ],
      "awards": [],
      "fun_fact": "Named after the French horror film. Billy Idol wanted to show a vulnerable side different from his punk image. The whispered French vocals add to the haunting atmosphere.",
      "fun_fact_de": "[DE] Named after the French horror film. Billy Idol wanted to show a vulnerable side ...",
      "fun_fact_es": "[ES] Named after the French horror film. Billy Idol wanted to show a vulnerable side ...",
      "uri_apple_music": "applemusic://track/217490782",
      "uri_youtube_music": "https://music.youtube.com/watch?v=9OFpfTd0EIs",
      "uri_tidal": "tidal://track/393348"
    },
    {
      "year": 1981,
      "uri": "spotify:track:5l3zkjO2Ag05TTqpbGQ9qP",
      "artist": "Ultravox",
      "alt_artists": [
        "Duran Duran",
        "OMD"
      ],
      "title": "Vienna - 2008 Remastered Version",
      "chart_info": {
        "billboard_peak": 0,
        "uk_peak": 2,
        "weeks_on_chart": 14
      },
      "certifications": [
        "Gold (UK)"
      ],
      "awards": [],
      "fun_fact": "Famously kept off #1 in the UK by Joe Dolce's 'Shaddap You Face'. The epic synth ballad is considered one of the greatest songs to never reach #1 in Britain.",
      "fun_fact_de": "[DE] Famously kept off #1 in the UK by Joe Dolce's 'Shaddap You Face'. The epic synth...",
      "fun_fact_es": "[ES] Famously kept off #1 in the UK by Joe Dolce's 'Shaddap You Face'. The epic synth...",
      "uri_apple_music": "applemusic://track/1630208751",
      "uri_youtube_music": "https://music.youtube.com/watch?v=xJeWySiuq1I",
      "uri_tidal": "tidal://track/11842696"
    },
    {
      "year": 1990,
      "uri": "spotify:track:5nydh0uIcz9gxSoJY6FtTn",
      "artist": "Winger",
      "alt_artists": [
        "Warrant",
        "Firehouse"
      ],
      "title": "Miles Away",
      "chart_info": {
        "billboard_peak": 12,
        "uk_peak": 56,
        "weeks_on_chart": 14
      },
      "certifications": [
        "Gold (US)"
      ],
      "awards": [],
      "fun_fact": "Written by Kip Winger about being away from loved ones on tour. The ballad showcased his classically-trained musical abilities beyond hair metal.",
      "fun_fact_de": "[DE] Written by Kip Winger about being away from loved ones on tour. The ballad showc...",
      "fun_fact_es": "[ES] Written by Kip Winger about being away from loved ones on tour. The ballad showc...",
      "uri_apple_music": "applemusic://track/1727217596",
      "uri_youtube_music": "https://music.youtube.com/watch?v=JMKPQKU61QI",
      "uri_tidal": "tidal://track/2571006"
    },
    {
      "year": 2001,
      "uri": "spotify:track:5prTs2HAw2G4idHZyeFp8o",
      "artist": "Staind",
      "alt_artists": [
        "Godsmack",
        "Puddle of Mudd"
      ],
      "title": "Outside",
      "chart_info": {
        "billboard_peak": 56,
        "uk_peak": 33,
        "weeks_on_chart": 12
      },
      "certifications": [
        "Gold (US)"
      ],
      "awards": [],
      "fun_fact": "Originally performed as a duet with Fred Durst at Woodstock '99. The raw emotional performance went viral and launched Staind's mainstream career.",
      "fun_fact_de": "[DE] Originally performed as a duet with Fred Durst at Woodstock '99. The raw emotion...",
      "fun_fact_es": "[ES] Originally performed as a duet with Fred Durst at Woodstock '99. The raw emotion...",
      "uri_apple_music": "applemusic://track/355893546",
      "uri_youtube_music": "https://music.youtube.com/watch?v=mVQpfoqsY8Q",
      "uri_tidal": "tidal://track/3392919"
    },
    {
      "year": 1981,
      "uri": "spotify:track:5t5rCnsgRBtcKqTB7SbD1Q",
      "artist": "Foreigner",
      "alt_artists": [
        "Journey",
        "REO Speedwagon"
      ],
      "title": "Waiting for a Girl like You - 2008 Remaster",
      "chart_info": {
        "billboard_peak": 2,
        "uk_peak": 8,
        "weeks_on_chart": 24
      },
      "certifications": [
        "Platinum (US)",
        "Silver (UK)"
      ],
      "awards": [],
      "fun_fact": "Spent 10 weeks at #2, blocked from #1 by Olivia Newton-John's 'Physical'. Mick Jones wrote it about his idealized vision of true love.",
      "fun_fact_de": "[DE] Spent 10 weeks at #2, blocked from #1 by Olivia Newton-John's 'Physical'. Mick J...",
      "fun_fact_es": "[ES] Spent 10 weeks at #2, blocked from #1 by Olivia Newton-John's 'Physical'. Mick J...",
      "uri_apple_music": "applemusic://track/321975428",
      "uri_youtube_music": "https://music.youtube.com/watch?v=2dWmKSj5HjI",
      "uri_tidal": "tidal://track/3029519"
    },
    {
      "year": 1978,
      "uri": "spotify:track:5wG0fxX1Ag3Xx4wACyUQMh",
      "artist": "Meat Loaf",
      "alt_artists": [
        "Bonnie Tyler",
        "Jim Steinman"
      ],
      "title": "Two Out of Three Ain't Bad",
      "chart_info": {
        "billboard_peak": 11,
        "uk_peak": 32,
        "weeks_on_chart": 15
      },
      "certifications": [
        "Platinum (US)"
      ],
      "awards": [],
      "fun_fact": "Jim Steinman wrote this as a response to Elvis Presley's 'I Want You, I Need You, I Love You'. The epic production style became Meat Loaf's signature.",
      "fun_fact_de": "[DE] Jim Steinman wrote this as a response to Elvis Presley's 'I Want You, I Need You...",
      "fun_fact_es": "[ES] Jim Steinman wrote this as a response to Elvis Presley's 'I Want You, I Need You...",
      "uri_apple_music": "applemusic://track/991385388",
      "uri_youtube_music": "https://music.youtube.com/watch?v=k5hWWe-ts2s",
      "uri_tidal": "tidal://track/1894031"
    },
    {
      "year": 1990,
      "uri": "spotify:track:5zOscWzPLc4tJ9d7pScHSR",
      "artist": "Sinéad O'Connor",
      "alt_artists": [
        "Sinead O'Connor",
        "Enya"
      ],
      "title": "Nothing Compares 2 U - 2009 Remastered Version",
      "chart_info": {
        "billboard_peak": 1,
        "uk_peak": 1,
        "weeks_on_chart": 19
      },
      "certifications": [
        "Platinum (US)",
        "Platinum (UK)"
      ],
      "awards": [],
      "fun_fact": "Written by Prince in 1985 for The Family. Sinéad's stark video, shot in one take with a single tear, became one of MTV's most iconic moments.",
      "fun_fact_de": "[DE] Written by Prince in 1985 for The Family. Sinéad's stark video, shot in one take...",
      "fun_fact_es": "[ES] Written by Prince in 1985 for The Family. Sinéad's stark video, shot in one take...",
      "uri_apple_music": "applemusic://track/1629185307",
      "uri_youtube_music": "https://music.youtube.com/watch?v=0-EF60neguk",
      "uri_tidal": "tidal://track/10904532"
    },
    {
      "year": 1985,
      "uri": "spotify:track:66BoRmfgo89gDmqwrYYIdU",
      "artist": "REO Speedwagon",
      "alt_artists": [
        "Styx",
        "Journey"
      ],
      "title": "Can't Fight This Feeling",
      "chart_info": {
        "billboard_peak": 1,
        "uk_peak": 16,
        "weeks_on_chart": 18
      },
      "certifications": [
        "Platinum (US)"
      ],
      "awards": [],
      "fun_fact": "Kevin Cronin started writing this in 1978 but couldn't finish it for years. It became one of the definitive power ballads and REO's second #1 hit.",
      "fun_fact_de": "[DE] Kevin Cronin started writing this in 1978 but couldn't finish it for years. It b...",
      "fun_fact_es": "[ES] Kevin Cronin started writing this in 1978 but couldn't finish it for years. It b...",
      "uri_apple_music": "applemusic://track/200299602",
      "uri_youtube_music": "https://music.youtube.com/watch?v=zpOULjyy-n8",
      "uri_tidal": "tidal://track/233192935"
    },
    {
      "year": 1987,
      "uri": "spotify:track:6B6aCxSBsECsulzOkJRxGv",
      "artist": "Fleetwood Mac",
      "alt_artists": [
        "Eagles",
        "Heart"
      ],
      "title": "Big Love",
      "chart_info": {
        "billboard_peak": 5,
        "uk_peak": 9,
        "weeks_on_chart": 15
      },
      "certifications": [
        "Gold (US)"
      ],
      "awards": [],
      "fun_fact": "Written by Lindsey Buckingham about his complicated feelings for Stevie Nicks. His intricate acoustic guitar work became legendary in live performances.",
      "fun_fact_de": "[DE] Written by Lindsey Buckingham about his complicated feelings for Stevie Nicks. H...",
      "fun_fact_es": "[ES] Written by Lindsey Buckingham about his complicated feelings for Stevie Nicks. H...",
      "uri_apple_music": "applemusic://track/202272743",
      "uri_youtube_music": "https://music.youtube.com/watch?v=4hPv6EuV7dM",
      "uri_tidal": "tidal://track/614307"
    },
    {
      "year": 2002,
      "uri": "spotify:track:6HzZhqXNyfJxuvQ9zfCc1U",
      "artist": "Daniel Bedingfield",
      "alt_artists": [
        "James Blunt",
        "Jason Mraz"
      ],
      "title": "If You're Not The One",
      "chart_info": {
        "billboard_peak": 15,
        "uk_peak": 1,
        "weeks_on_chart": 16
      },
      "certifications": [
        "Gold (US)",
        "Platinum (UK)"
      ],
      "awards": [],
      "fun_fact": "Daniel wrote this at age 17, asking existential questions about soulmates. He recorded early demos in his bedroom, launching the bedroom producer trend.",
      "fun_fact_de": "[DE] Daniel wrote this at age 17, asking existential questions about soulmates. He re...",
      "fun_fact_es": "[ES] Daniel wrote this at age 17, asking existential questions about soulmates. He re...",
      "uri_apple_music": "applemusic://track/476986080",
      "uri_youtube_music": "https://music.youtube.com/watch?v=j6nevGNYTkA",
      "uri_tidal": "tidal://track/1852738"
    },
    {
      "year": 1986,
      "uri": "spotify:track:6Kh4FkETk9i3EUVTerZEuY",
      "artist": "Van Halen",
      "alt_artists": [
        "Bon Jovi",
        "Def Leppard"
      ],
      "title": "Love Walks In - 2004 Remaster",
      "chart_info": {
        "billboard_peak": 22,
        "uk_peak": 59,
        "weeks_on_chart": 12
      },
      "certifications": [],
      "awards": [],
      "fun_fact": "Sammy Hagar wrote this after a dream about an alien visitation. The song showcased Van Halen's evolved sound with keyboards prominent in the arrangement.",
      "fun_fact_de": "[DE] Sammy Hagar wrote this after a dream about an alien visitation. The song showcas...",
      "fun_fact_es": "[ES] Sammy Hagar wrote this after a dream about an alien visitation. The song showcas...",
      "uri_apple_music": "applemusic://track/319402893",
      "uri_youtube_music": "https://music.youtube.com/watch?v=8qcQ34iTswY",
      "uri_tidal": "tidal://track/14219182"
    },
    {
      "year": 2004,
      "uri": "spotify:track:6Nq8YtPAHuL1outooeiFde",
      "artist": "Velvet Revolver",
      "alt_artists": [
        "Guns N' Roses",
        "Stone Temple Pilots"
      ],
      "title": "Fall to Pieces",
      "chart_info": {
        "billboard_peak": 67,
        "uk_peak": 24,
        "weeks_on_chart": 10
      },
      "certifications": [],
      "awards": [],
      "fun_fact": "Written about addiction struggles, it resonated deeply with the supergroup's members - former Guns N' Roses and Stone Temple Pilots musicians.",
      "fun_fact_de": "[DE] Written about addiction struggles, it resonated deeply with the supergroup's mem...",
      "fun_fact_es": "[ES] Written about addiction struggles, it resonated deeply with the supergroup's mem...",
      "uri_apple_music": "applemusic://track/303178195",
      "uri_youtube_music": "https://music.youtube.com/watch?v=9JhsUFuqbCM",
      "uri_tidal": "tidal://track/2865114"
    },
    {
      "year": 1991,
      "uri": "spotify:track:6Ub4EjfFJUuGnVV9xWPCIV",
      "artist": "STEELHEART",
      "alt_artists": [
        "Firehouse",
        "Slaughter"
      ],
      "title": "I'll Never Let You Go",
      "chart_info": {
        "billboard_peak": 14,
        "uk_peak": 68,
        "weeks_on_chart": 14
      },
      "certifications": [
        "Gold (US)"
      ],
      "awards": [],
      "fun_fact": "Miljenko Matijevic's incredible 5-octave vocal range is showcased in this power ballad. The band was poised for stardom before grunge changed the musical landscape.",
      "fun_fact_de": "[DE] Miljenko Matijevic's incredible 5-octave vocal range is showcased in this power ...",
      "fun_fact_es": "[ES] Miljenko Matijevic's incredible 5-octave vocal range is showcased in this power ...",
      "uri_apple_music": "applemusic://track/1660628664",
      "uri_youtube_music": "https://music.youtube.com/watch?v=F-nyeiKk35M",
      "uri_tidal": "tidal://track/14338595"
    },
    {
      "year": 1984,
      "uri": "spotify:track:6miB3at8s4itUuLbbSpAUo",
      "artist": "Phil Collins",
      "alt_artists": [
        "Genesis",
        "Peter Gabriel"
      ],
      "title": "Against All Odds (Take A Look At Me Now)",
      "chart_info": {
        "billboard_peak": 1,
        "uk_peak": 2,
        "weeks_on_chart": 19
      },
      "certifications": [
        "Platinum (US)",
        "Gold (UK)"
      ],
      "awards": [],
      "fun_fact": "Written for the film Against All Odds. Phil Collins wrote and recorded it in a single day after watching a rough cut of the film. It won a Grammy.",
      "fun_fact_de": "[DE] Written for the film Against All Odds. Phil Collins wrote and recorded it in a s...",
      "fun_fact_es": "[ES] Written for the film Against All Odds. Phil Collins wrote and recorded it in a s...",
      "uri_apple_music": "applemusic://track/1606706137",
      "uri_youtube_music": "https://music.youtube.com/watch?v=wuvtoyVi7vY",
      "uri_tidal": "tidal://track/462054967"
    },
    {
      "year": 1988,
      "uri": "spotify:track:6r4laxAXabuv6pK9Nzoskc",
      "artist": "Aerosmith",
      "alt_artists": [
        "Bon Jovi",
        "Def Leppard"
      ],
      "title": "Angel",
      "chart_info": {
        "billboard_peak": 3,
        "uk_peak": 69,
        "weeks_on_chart": 16
      },
      "certifications": [
        "Gold (US)"
      ],
      "awards": [],
      "fun_fact": "Written by Steven Tyler and Desmond Child about Tyler's daughter. The tender ballad showed Aerosmith's softer side during their commercial comeback.",
      "fun_fact_de": "[DE] Written by Steven Tyler and Desmond Child about Tyler's daughter. The tender bal...",
      "fun_fact_es": "[ES] Written by Steven Tyler and Desmond Child about Tyler's daughter. The tender bal...",
      "uri_apple_music": "applemusic://track/1440823557",
      "uri_youtube_music": "https://music.youtube.com/watch?v=CBTOGVb_cQg",
      "uri_tidal": "tidal://track/574517"
    },
    {
      "year": 1995,
      "uri": "spotify:track:6uVGkBiE3ABDdJPn2Q4bLu",
      "artist": "Def Leppard",
      "alt_artists": [
        "Bon Jovi",
        "Whitesnake"
      ],
      "title": "When Love & Hate Collide",
      "chart_info": {
        "billboard_peak": 58,
        "uk_peak": 2,
        "weeks_on_chart": 14
      },
      "certifications": [
        "Silver (UK)"
      ],
      "awards": [],
      "fun_fact": "Originally recorded for the Adrenalize album but held back. It became a massive hit in the UK and showed Def Leppard could still deliver emotional ballads.",
      "fun_fact_de": "[DE] Originally recorded for the Adrenalize album but held back. It became a massive ...",
      "fun_fact_es": "[ES] Originally recorded for the Adrenalize album but held back. It became a massive ...",
      "uri_apple_music": "applemusic://track/1434883426",
      "uri_youtube_music": "https://music.youtube.com/watch?v=d7ew_jIxLa8",
      "uri_tidal": "tidal://track/94406416"
    },
    {
      "year": 1983,
      "uri": "spotify:track:6vrUTGn5p8IrfTZ0J6sIVM",
      "artist": "Journey",
      "alt_artists": [
        "Foreigner",
        "REO Speedwagon"
      ],
      "title": "Faithfully",
      "chart_info": {
        "billboard_peak": 12,
        "uk_peak": 59,
        "weeks_on_chart": 15
      },
      "certifications": [
        "Gold (US)"
      ],
      "awards": [],
      "fun_fact": "Jonathan Cain wrote this on a tour bus, reflecting on how touring affects relationships. Steve Perry's emotional delivery made it a wedding song classic.",
      "fun_fact_de": "[DE] Jonathan Cain wrote this on a tour bus, reflecting on how touring affects relati...",
      "fun_fact_es": "[ES] Jonathan Cain wrote this on a tour bus, reflecting on how touring affects relati...",
      "uri_apple_music": "applemusic://track/1109658204",
      "uri_youtube_music": "https://music.youtube.com/watch?v=OMD8hBsA-RI",
      "uri_tidal": "tidal://track/1211254"
    },
    {
      "year": 2002,
      "uri": "spotify:track:6weQnAmZRMyiMrZsyrhfYn",
      "artist": "Stone Sour",
      "alt_artists": [
        "Slipknot",
        "Disturbed"
      ],
      "title": "Bother",
      "chart_info": {
        "billboard_peak": 56,
        "uk_peak": 44,
        "weeks_on_chart": 11
      },
      "certifications": [],
      "awards": [],
      "fun_fact": "Corey Taylor wrote this acoustic ballad for the Spider-Man soundtrack. It showed a vulnerable side of the Slipknot/Stone Sour frontman.",
      "fun_fact_de": "[DE] Corey Taylor wrote this acoustic ballad for the Spider-Man soundtrack. It showed...",
      "fun_fact_es": "[ES] Corey Taylor wrote this acoustic ballad for the Spider-Man soundtrack. It showed...",
      "uri_apple_music": "applemusic://track/355893847",
      "uri_youtube_music": "https://music.youtube.com/watch?v=Q-pXD0FXLQ8",
      "uri_tidal": "tidal://track/1919983"
    },
    {
      "year": 1972,
      "uri": "spotify:track:73bVYFCVJN1YwCSyRjEslG",
      "artist": "Black Sabbath",
      "alt_artists": [
        "Ozzy Osbourne",
        "Deep Purple"
      ],
      "title": "Changes",
      "chart_info": {
        "billboard_peak": 0,
        "uk_peak": 0,
        "weeks_on_chart": 0
      },
      "certifications": [],
      "awards": [],
      "fun_fact": "The only ballad on Black Sabbath's Vol. 4 album. Tony Iommi played piano for the first time on record, creating an unexpectedly tender moment in heavy metal.",
      "fun_fact_de": "[DE] The only ballad on Black Sabbath's Vol. 4 album. Tony Iommi played piano for the...",
      "fun_fact_es": "[ES] The only ballad on Black Sabbath's Vol. 4 album. Tony Iommi played piano for the...",
      "uri_apple_music": "applemusic://track/696375679",
      "uri_youtube_music": "https://music.youtube.com/watch?v=_eBCxYVma1g",
      "uri_tidal": "tidal://track/1500870"
    },
    {
      "year": 1986,
      "uri": "spotify:track:779ooI3rBd0CLqCiiJmtVo",
      "artist": "Glass Tiger",
      "alt_artists": [
        "Bryan Adams",
        "Loverboy"
      ],
      "title": "Don't Forget Me (When I'm Gone)",
      "chart_info": {
        "billboard_peak": 2,
        "uk_peak": 29,
        "weeks_on_chart": 16
      },
      "certifications": [
        "Gold (US)"
      ],
      "awards": [],
      "fun_fact": "This Canadian band's breakthrough hit featured Bryan Adams on backing vocals. It captured the quintessential 80s power ballad sound.",
      "fun_fact_de": "[DE] This Canadian band's breakthrough hit featured Bryan Adams on backing vocals. It...",
      "fun_fact_es": "[ES] This Canadian band's breakthrough hit featured Bryan Adams on backing vocals. It...",
      "uri_apple_music": "applemusic://track/724500900",
      "uri_youtube_music": "https://music.youtube.com/watch?v=Jx6_-urg5fo",
      "uri_tidal": "tidal://track/1108913"
    },
    {
      "year": 1989,
      "uri": "spotify:track:78FzQfooQzB43sGzlpI2At",
      "artist": "Skid Row",
      "alt_artists": [
        "Bon Jovi",
        "Mötley Crüe"
      ],
      "title": "18 and Life",
      "chart_info": {
        "billboard_peak": 4,
        "uk_peak": 12,
        "weeks_on_chart": 17
      },
      "certifications": [
        "Gold (US)",
        "Silver (UK)"
      ],
      "awards": [],
      "fun_fact": "Written about a troubled youth. Sebastian Bach's powerful vocals and the song's narrative structure made it one of the defining late-80s power ballads.",
      "fun_fact_de": "[DE] Written about a troubled youth. Sebastian Bach's powerful vocals and the song's ...",
      "fun_fact_es": "[ES] Written about a troubled youth. Sebastian Bach's powerful vocals and the song's ...",
      "uri_apple_music": "applemusic://track/693227789",
      "uri_youtube_music": "https://music.youtube.com/watch?v=Ghd2bkIadG4",
      "uri_tidal": "tidal://track/115810706"
    },
    {
      "year": 1978,
      "uri": "spotify:track:7AmdLtDBBMHWTvneMLm8Nj",
      "artist": "Kansas",
      "alt_artists": [
        "Styx",
        "Boston"
      ],
      "title": "Dust in the Wind",
      "chart_info": {
        "billboard_peak": 6,
        "uk_peak": 47,
        "weeks_on_chart": 15
      },
      "certifications": [
        "Gold (US)"
      ],
      "awards": [],
      "fun_fact": "Kerry Livgren wrote this after reading a poem about mortality. The acoustic fingerpicking pattern was inspired by classical guitarist Fernando Sor.",
      "fun_fact_de": "[DE] Kerry Livgren wrote this after reading a poem about mortality. The acoustic fing...",
      "fun_fact_es": "[ES] Kerry Livgren wrote this after reading a poem about mortality. The acoustic fing...",
      "uri_apple_music": "",
      "uri_youtube_music": "https://music.youtube.com/watch?v=tH2w6Oxx0kQ",
      "uri_tidal": "tidal://track/234636699"
    },
    {
      "year": 2003,
      "uri": "spotify:track:7CKbqqrs0AS1si1ZgaQdcj",
      "artist": "Evanescence",
      "alt_artists": [
        "Within Temptation",
        "Linkin Park"
      ],
      "title": "Bring Me To Life",
      "chart_info": {
        "billboard_peak": 5,
        "uk_peak": 1,
        "weeks_on_chart": 18
      },
      "certifications": [
        "2x Platinum (US)",
        "Platinum (UK)"
      ],
      "awards": [],
      "fun_fact": "The label insisted on Paul McCoy's male vocals, though Amy Lee originally wrote it as a solo. The song's unique rock/orchestral blend launched the genre.",
      "fun_fact_de": "[DE] The label insisted on Paul McCoy's male vocals, though Amy Lee originally wrote ...",
      "fun_fact_es": "[ES] The label insisted on Paul McCoy's male vocals, though Amy Lee originally wrote ...",
      "uri_apple_music": "applemusic://track/727506102",
      "uri_youtube_music": "https://music.youtube.com/watch?v=3YxaaGgTQYM",
      "uri_tidal": "tidal://track/2876035"
    },
    {
      "year": 1989,
      "uri": "spotify:track:7EkFVRqmso1h8WjrUrlXIT",
      "artist": "Faster Pussycat",
      "alt_artists": [
        "L.A. Guns",
        "Pretty Boy Floyd"
      ],
      "title": "House of Pain",
      "chart_info": {
        "billboard_peak": 28,
        "uk_peak": 0,
        "weeks_on_chart": 11
      },
      "certifications": [],
      "awards": [],
      "fun_fact": "Taime Downe wrote this emotional ballad about personal struggles. It showed the glam metal band's ability to write sensitive material beyond party songs.",
      "fun_fact_de": "[DE] Taime Downe wrote this emotional ballad about personal struggles. It showed the ...",
      "fun_fact_es": "[ES] Taime Downe wrote this emotional ballad about personal struggles. It showed the ...",
      "uri_apple_music": "",
      "uri_youtube_music": "https://music.youtube.com/watch?v=eunWuKxfAC8",
      "uri_tidal": "tidal://track/1868118"
    },
    {
      "year": 1990,
      "uri": "spotify:track:7FTLcRHtraE56nzsEg1wJJ",
      "artist": "Guns N' Roses",
      "alt_artists": [
        "Skid Row",
        "Mötley Crüe"
      ],
      "title": "Don't Cry (Original)",
      "chart_info": {
        "billboard_peak": 0,
        "uk_peak": 0,
        "weeks_on_chart": 0
      },
      "certifications": [],
      "awards": [],
      "fun_fact": "A classic power ballad by Guns N' Roses.",
      "fun_fact_de": "",
      "fun_fact_es": "",
      "uri_apple_music": "applemusic://track/1605606761",
      "uri_youtube_music": "https://music.youtube.com/watch?v=zRIbf6JqkNc",
      "uri_tidal": "tidal://track/55172078"
    },
    {
      "year": 1981,
      "uri": "spotify:track:7ItNjcIhJCSJwonx9tOJ3Z",
      "artist": "KISS",
      "alt_artists": [
        "Alice Cooper",
        "Mötley Crüe"
      ],
      "title": "A World Without Heroes",
      "chart_info": {
        "billboard_peak": 56,
        "uk_peak": 55,
        "weeks_on_chart": 8
      },
      "certifications": [],
      "awards": [],
      "fun_fact": "Co-written with Lou Reed. This uncharacteristic ballad appeared during KISS's experimental phase and showcased Paul Stanley's vulnerable vocal delivery.",
      "fun_fact_de": "[DE] Co-written with Lou Reed. This uncharacteristic ballad appeared during KISS's ex...",
      "fun_fact_es": "[ES] Co-written with Lou Reed. This uncharacteristic ballad appeared during KISS's ex...",
      "uri_apple_music": "applemusic://track/977495542",
      "uri_youtube_music": "https://music.youtube.com/watch?v=A9SLgcNEpyM",
      "uri_tidal": "tidal://track/3268257"
    },
    {
      "year": 1986,
      "uri": "spotify:track:7KM52fyhuSxeIN1y2Sn6QL",
      "artist": "John Farnham",
      "alt_artists": [
        "Air Supply",
        "Little River Band"
      ],
      "title": "You're the Voice",
      "chart_info": {
        "billboard_peak": 82,
        "uk_peak": 6,
        "weeks_on_chart": 12
      },
      "certifications": [
        "Gold (UK)"
      ],
      "awards": [],
      "fun_fact": "Massive hit in Australia and Europe. The bagpipe-driven anthem became an unofficial Australian anthem and revitalized John Farnham's career.",
      "fun_fact_de": "[DE] Massive hit in Australia and Europe. The bagpipe-driven anthem became an unoffic...",
      "fun_fact_es": "[ES] Massive hit in Australia and Europe. The bagpipe-driven anthem became an unoffic...",
      "uri_apple_music": "applemusic://track/525521084",
      "uri_youtube_music": "https://music.youtube.com/watch?v=tbkOZTSvrHs",
      "uri_tidal": "tidal://track/1770105"
    },
    {
      "year": 1990,
      "uri": "spotify:track:7MH2Q5nO42kBU4UZ2WjLOI",
      "artist": "Alias",
      "alt_artists": [
        "Sheriff",
        "Survivor"
      ],
      "title": "More Than Words Can Say",
      "chart_info": {
        "billboard_peak": 2,
        "uk_peak": 72,
        "weeks_on_chart": 16
      },
      "certifications": [
        "Gold (US)"
      ],
      "awards": [],
      "fun_fact": "Written by Sheriff members who regrouped as Alias. The song continued their power ballad success following Sheriff's 'When I'm With You'.",
      "fun_fact_de": "[DE] Written by Sheriff members who regrouped as Alias. The song continued their powe...",
      "fun_fact_es": "[ES] Written by Sheriff members who regrouped as Alias. The song continued their powe...",
      "uri_apple_music": "applemusic://track/723338381",
      "uri_youtube_music": "https://music.youtube.com/watch?v=pjhrGPFaQoQ",
      "uri_tidal": "tidal://track/1411755"
    },
    {
      "year": 2001,
      "uri": "spotify:track:7Mz9qPB9hp1rXBgXvrVAST",
      "artist": "Enrique Iglesias",
      "alt_artists": [
        "Ricky Martin",
        "Marc Anthony"
      ],
      "title": "Hero",
      "chart_info": {
        "billboard_peak": 3,
        "uk_peak": 1,
        "weeks_on_chart": 18
      },
      "certifications": [
        "Platinum (US)",
        "Platinum (UK)"
      ],
      "awards": [],
      "fun_fact": "Originally offered to several other artists who turned it down. Enrique recorded an English and Spanish version, with the English version becoming his signature song.",
      "fun_fact_de": "[DE] Originally offered to several other artists who turned it down. Enrique recorded...",
      "fun_fact_es": "[ES] Originally offered to several other artists who turned it down. Enrique recorded...",
      "uri_apple_music": "applemusic://track/697410052",
      "uri_youtube_music": "https://music.youtube.com/watch?v=koJlIGDImiU",
      "uri_tidal": "tidal://track/1375869"
    },
    {
      "year": 1990,
      "uri": "spotify:track:7afSN5zhUhkbpRFpYKYztK",
      "artist": "Firehouse",
      "alt_artists": [
        "Winger",
        "Warrant"
      ],
      "title": "Love of a Lifetime (2024 Remaster)",
      "chart_info": {
        "billboard_peak": 0,
        "uk_peak": 0,
        "weeks_on_chart": 0
      },
      "certifications": [],
      "awards": [],
      "fun_fact": "A classic power ballad by Firehouse.",
      "fun_fact_de": "",
      "fun_fact_es": "",
      "uri_apple_music": "applemusic://track/1452924289",
      "uri_youtube_music": "https://music.youtube.com/watch?v=5ETENrv8cnU",
      "uri_tidal": "tidal://track/76773928"
    },
    {
      "year": 2000,
      "uri": "spotify:track:7bDnK1pJ6rXxVwCdhiepdZ",
      "artist": "Creed",
      "alt_artists": [
        "Nickelback",
        "3 Doors Down"
      ],
      "title": "With Arms Wide Open",
      "chart_info": {
        "billboard_peak": 1,
        "uk_peak": 13,
        "weeks_on_chart": 20
      },
      "certifications": [
        "2x Platinum (US)"
      ],
      "awards": [],
      "fun_fact": "Scott Stapp wrote this after learning he would become a father. It won the Grammy for Best Rock Song and became Creed's only #1 hit.",
      "fun_fact_de": "[DE] Scott Stapp wrote this after learning he would become a father. It won the Gramm...",
      "fun_fact_es": "[ES] Scott Stapp wrote this after learning he would become a father. It won the Gramm...",
      "uri_apple_music": "applemusic://track/1716253895",
      "uri_youtube_music": "https://music.youtube.com/watch?v=99j0zLuNhi8",
      "uri_tidal": "tidal://track/168381910"
    },
    {
      "year": 1988,
      "uri": "spotify:track:7o10Pto0YFchZl1zL4dLPH",
      "artist": "Lita Ford",
      "alt_artists": [
        "Joan Jett",
        "Vixen"
      ],
      "title": "Lisa",
      "chart_info": {
        "billboard_peak": 0,
        "uk_peak": 0,
        "weeks_on_chart": 0
      },
      "certifications": [],
      "awards": [],
      "fun_fact": "From Lita Ford's hit album 'Lita'. The former Runaways guitarist showed her range with power ballads alongside her harder rock material.",
      "fun_fact_de": "[DE] From Lita Ford's hit album 'Lita'. The former Runaways guitarist showed her rang...",
      "fun_fact_es": "[ES] From Lita Ford's hit album 'Lita'. The former Runaways guitarist showed her rang...",
      "uri_apple_music": "applemusic://track/1423285054",
      "uri_youtube_music": "https://music.youtube.com/watch?v=rPX-JiTvDeY",
      "uri_tidal": "tidal://track/97708782"
    },
    {
      "year": 1988,
      "uri": "spotify:track:7z0JcZ8PQoAfUaLIXvbyTH",
      "artist": "Cheap Trick",
      "alt_artists": [
        "The Knack",
        "The Romantics"
      ],
      "title": "The Flame",
      "chart_info": {
        "billboard_peak": 1,
        "uk_peak": 16,
        "weeks_on_chart": 19
      },
      "certifications": [
        "Gold (US)"
      ],
      "awards": [],
      "fun_fact": "Written by outside songwriters, which the band initially resisted. It became Cheap Trick's only #1 hit in the US, though they rarely play it live.",
      "fun_fact_de": "[DE] Written by outside songwriters, which the band initially resisted. It became Che...",
      "fun_fact_es": "[ES] Written by outside songwriters, which the band initially resisted. It became Che...",
      "uri_apple_music": "applemusic://track/1445752097",
      "uri_youtube_music": "https://music.youtube.com/watch?v=2u6uXuT9pm4",
      "uri_tidal": "tidal://track/39650336"
    }
  ]
}
